{"SPDXID":"SPDXRef-DOCUMENT","spdxVersion":"SPDX-2.3","creationInfo":{"created":"2023-05-15T15:37:56Z","creators":["Tool: GitHub.com-Dependency-Graph"]},"name":"com.github.mybatis/mybatis-3","dataLicense":"CC0-1.0","documentDescribes":["SPDXRef-com.github.mybatis-mybatis-3"],"documentNamespace":"https://github.com/mybatis/mybatis-3/dependency_graph/sbom-9e72f89178726525","packages":[{"SPDXID":"SPDXRef-com.github.mybatis-mybatis-3","name":"com.github.mybatis/mybatis-3","versionInfo":"","downloadLocation":"NOASSERTION","filesAnalyzed":false,"licenseConcluded":"NOASSERTION","licenseDeclared":"NOASSERTION","supplier":"NOASSERTION"},{"SPDXID":"SPDXRef-maven-cglib-cglib-3.3.0","name":"maven:cglib:cglib","versionInfo":"3.3.0","downloadLocation":"NOASSERTION","filesAnalyzed":false,"licenseConcluded":"Apache-2.0","licenseDeclared":"NOASSERTION","supplier":"NOASSERTION","externalRefs":[{"referenceCategory":"PACKAGE-MANAGER","referenceLocator":"pkg:maven/cglib/cglib@3.3.0","referenceType":"purl"}]},{"SPDXID":"SPDXRef-maven-ch.qos.logback-logback-classic-1.2.10","name":"maven:ch.qos.logback:logback-classic","versionInfo":"1.2.10","downloadLocation":"NOASSERTION","filesAnalyzed":false,"licenseConcluded":"LGPL-2.1","licenseDeclared":"NOASSERTION","supplier":"NOASSERTION","externalRefs":[{"referenceCategory":"PACKAGE-MANAGER","referenceLocator":"pkg:maven/ch.qos.logback/logback-classic@1.2.10","referenceType":"purl"}]},{"SPDXID":"SPDXRef-maven-ch.qos.logback-logback-classic-1.2.11","name":"maven:ch.qos.logback:logback-classic","versionInfo":"1.2.11","downloadLocation":"NOASSERTION","filesAnalyzed":false,"licenseConcluded":"LGPL-2.1","licenseDeclared":"NOASSERTION","supplier":"NOASSERTION","externalRefs":[{"referenceCategory":"PACKAGE-MANAGER","referenceLocator":"pkg:maven/ch.qos.logback/logback-classic@1.2.11","referenceType":"purl"}]},{"SPDXID":"SPDXRef-maven-ch.qos.logback-logback-classic-1.3.0","name":"maven:ch.qos.logback:logback-classic","versionInfo":"1.3.0","downloadLocation":"NOASSERTION","filesAnalyzed":false,"licenseConcluded":"LGPL-2.1","licenseDeclared":"NOASSERTION","supplier":"NOASSERTION","externalRefs":[{"referenceCategory":"PACKAGE-MANAGER","referenceLocator":"pkg:maven/ch.qos.logback/logback-classic@1.3.0","referenceType":"purl"}]},{"SPDXID":"SPDXRef-maven-ch.qos.logback-logback-classic-1.4.1","name":"maven:ch.qos.logback:logback-classic","versionInfo":"1.4.1","downloadLocation":"NOASSERTION","filesAnalyzed":false,"licenseConcluded":"LGPL-2.1","licenseDeclared":"NOASSERTION","supplier":"NOASSERTION","externalRefs":[{"referenceCategory":"PACKAGE-MANAGER","referenceLocator":"pkg:maven/ch.qos.logback/logback-classic@1.4.1","referenceType":"purl"}]},{"SPDXID":"SPDXRef-maven-ch.qos.logback-logback-classic-1.4.2","name":"maven:ch.qos.logback:logback-classic","versionInfo":"1.4.2","downloadLocation":"NOASSERTION","filesAnalyzed":false,"licenseConcluded":"LGPL-2.1","licenseDeclared":"NOASSERTION","supplier":"NOASSERTION","externalRefs":[{"referenceCategory":"PACKAGE-MANAGER","referenceLocator":"pkg:maven/ch.qos.logback/logback-classic@1.4.2","referenceType":"purl"}]},{"SPDXID":"SPDXRef-maven-ch.qos.logback-logback-classic-1.4.3","name":"maven:ch.qos.logback:logback-classic","versionInfo":"1.4.3","downloadLocation":"NOASSERTION","filesAnalyzed":false,"licenseConcluded":"LGPL-2.1","licenseDeclared":"NOASSERTION","supplier":"NOASSERTION","externalRefs":[{"referenceCategory":"PACKAGE-MANAGER","referenceLocator":"pkg:maven/ch.qos.logback/logback-classic@1.4.3","referenceType":"purl"}]},{"SPDXID":"SPDXRef-maven-ch.qos.logback-logback-classic-1.4.4","name":"maven:ch.qos.logback:logback-classic","versionInfo":"1.4.4","downloadLocation":"NOASSERTION","filesAnalyzed":false,"licenseConcluded":"LGPL-2.1","licenseDeclared":"NOASSERTION","supplier":"NOASSERTION","externalRefs":[{"referenceCategory":"PACKAGE-MANAGER","referenceLocator":"pkg:maven/ch.qos.logback/logback-classic@1.4.4","referenceType":"purl"}]},{"SPDXID":"SPDXRef-maven-ch.qos.logback-logback-classic-1.4.5","name":"maven:ch.qos.logback:logback-classic","versionInfo":"1.4.5","downloadLocation":"NOASSERTION","filesAnalyzed":false,"licenseConcluded":"LGPL-2.1","licenseDeclared":"NOASSERTION","supplier":"NOASSERTION","externalRefs":[{"referenceCategory":"PACKAGE-MANAGER","referenceLocator":"pkg:maven/ch.qos.logback/logback-classic@1.4.5","referenceType":"purl"}]},{"SPDXID":"SPDXRef-maven-ch.qos.logback-logback-classic-1.4.6","name":"maven:ch.qos.logback:logback-classic","versionInfo":"1.4.6","downloadLocation":"NOASSERTION","filesAnalyzed":false,"licenseConcluded":"LGPL-2.1","licenseDeclared":"NOASSERTION","supplier":"NOASSERTION","externalRefs":[{"referenceCategory":"PACKAGE-MANAGER","referenceLocator":"pkg:maven/ch.qos.logback/logback-classic@1.4.6","referenceType":"purl"}]},{"SPDXID":"SPDXRef-maven-ch.qos.logback-logback-classic-1.4.7","name":"maven:ch.qos.logback:logback-classic","versionInfo":"1.4.7","downloadLocation":"NOASSERTION","filesAnalyzed":false,"licenseConcluded":"LGPL-2.1","licenseDeclared":"NOASSERTION","supplier":"NOASSERTION","externalRefs":[{"referenceCategory":"PACKAGE-MANAGER","referenceLocator":"pkg:maven/ch.qos.logback/logback-classic@1.4.7","referenceType":"purl"}]},{"SPDXID":"SPDXRef-maven-ch.qos.reload4j-reload4j-1.2.18.3","name":"maven:ch.qos.reload4j:reload4j","versionInfo":"1.2.18.3","downloadLocation":"NOASSERTION","filesAnalyzed":false,"licenseConcluded":"Apache-2.0","licenseDeclared":"NOASSERTION","supplier":"NOASSERTION","externalRefs":[{"referenceCategory":"PACKAGE-MANAGER","referenceLocator":"pkg:maven/ch.qos.reload4j/reload4j@1.2.18.3","referenceType":"purl"}]},{"SPDXID":"SPDXRef-maven-ch.qos.reload4j-reload4j-1.2.18.4","name":"maven:ch.qos.reload4j:reload4j","versionInfo":"1.2.18.4","downloadLocation":"NOASSERTION","filesAnalyzed":false,"licenseConcluded":"Apache-2.0","licenseDeclared":"NOASSERTION","supplier":"NOASSERTION","externalRefs":[{"referenceCategory":"PACKAGE-MANAGER","referenceLocator":"pkg:maven/ch.qos.reload4j/reload4j@1.2.18.4","referenceType":"purl"}]},{"SPDXID":"SPDXRef-maven-ch.qos.reload4j-reload4j-1.2.18.5","name":"maven:ch.qos.reload4j:reload4j","versionInfo":"1.2.18.5","downloadLocation":"NOASSERTION","filesAnalyzed":false,"licenseConcluded":"Apache-2.0","licenseDeclared":"NOASSERTION","supplier":"NOASSERTION","externalRefs":[{"referenceCategory":"PACKAGE-MANAGER","referenceLocator":"pkg:maven/ch.qos.reload4j/reload4j@1.2.18.5","referenceType":"purl"}]},{"SPDXID":"SPDXRef-maven-ch.qos.reload4j-reload4j-1.2.19","name":"maven:ch.qos.reload4j:reload4j","versionInfo":"1.2.19","downloadLocation":"NOASSERTION","filesAnalyzed":false,"licenseConcluded":"Apache-2.0","licenseDeclared":"NOASSERTION","supplier":"NOASSERTION","externalRefs":[{"referenceCategory":"PACKAGE-MANAGER","referenceLocator":"pkg:maven/ch.qos.reload4j/reload4j@1.2.19","referenceType":"purl"}]},{"SPDXID":"SPDXRef-maven-ch.qos.reload4j-reload4j-1.2.20","name":"maven:ch.qos.reload4j:reload4j","versionInfo":"1.2.20","downloadLocation":"NOASSERTION","filesAnalyzed":false,"licenseConcluded":"Apache-2.0","licenseDeclared":"NOASSERTION","supplier":"NOASSERTION","externalRefs":[{"referenceCategory":"PACKAGE-MANAGER","referenceLocator":"pkg:maven/ch.qos.reload4j/reload4j@1.2.20","referenceType":"purl"}]},{"SPDXID":"SPDXRef-maven-ch.qos.reload4j-reload4j-1.2.21","name":"maven:ch.qos.reload4j:reload4j","versionInfo":"1.2.21","downloadLocation":"NOASSERTION","filesAnalyzed":false,"licenseConcluded":"Apache-2.0","licenseDeclared":"NOASSERTION","supplier":"NOASSERTION","externalRefs":[{"referenceCategory":"PACKAGE-MANAGER","referenceLocator":"pkg:maven/ch.qos.reload4j/reload4j@1.2.21","referenceType":"purl"}]},{"SPDXID":"SPDXRef-maven-ch.qos.reload4j-reload4j-1.2.22","name":"maven:ch.qos.reload4j:reload4j","versionInfo":"1.2.22","downloadLocation":"NOASSERTION","filesAnalyzed":false,"licenseConcluded":"Apache-2.0","licenseDeclared":"NOASSERTION","supplier":"NOASSERTION","externalRefs":[{"referenceCategory":"PACKAGE-MANAGER","referenceLocator":"pkg:maven/ch.qos.reload4j/reload4j@1.2.22","referenceType":"purl"}]},{"SPDXID":"SPDXRef-maven-ch.qos.reload4j-reload4j-1.2.23","name":"maven:ch.qos.reload4j:reload4j","versionInfo":"1.2.23","downloadLocation":"NOASSERTION","filesAnalyzed":false,"licenseConcluded":"Apache-2.0","licenseDeclared":"NOASSERTION","supplier":"NOASSERTION","externalRefs":[{"referenceCategory":"PACKAGE-MANAGER","referenceLocator":"pkg:maven/ch.qos.reload4j/reload4j@1.2.23","referenceType":"purl"}]},{"SPDXID":"SPDXRef-maven-ch.qos.reload4j-reload4j-1.2.24","name":"maven:ch.qos.reload4j:reload4j","versionInfo":"1.2.24","downloadLocation":"NOASSERTION","filesAnalyzed":false,"licenseConcluded":"Apache-2.0","licenseDeclared":"NOASSERTION","supplier":"NOASSERTION","externalRefs":[{"referenceCategory":"PACKAGE-MANAGER","referenceLocator":"pkg:maven/ch.qos.reload4j/reload4j@1.2.24","referenceType":"purl"}]},{"SPDXID":"SPDXRef-maven-ch.qos.reload4j-reload4j-1.2.25","name":"maven:ch.qos.reload4j:reload4j","versionInfo":"1.2.25","downloadLocation":"NOASSERTION","filesAnalyzed":false,"licenseConcluded":"Apache-2.0","licenseDeclared":"NOASSERTION","supplier":"NOASSERTION","externalRefs":[{"referenceCategory":"PACKAGE-MANAGER","referenceLocator":"pkg:maven/ch.qos.reload4j/reload4j@1.2.25","referenceType":"purl"}]},{"SPDXID":"SPDXRef-maven-com.h2database-h2-2.1.210","name":"maven:com.h2database:h2","versionInfo":"2.1.210","downloadLocation":"NOASSERTION","filesAnalyzed":false,"licenseConcluded":"NOASSERTION","licenseDeclared":"NOASSERTION","supplier":"NOASSERTION","externalRefs":[{"referenceCategory":"PACKAGE-MANAGER","referenceLocator":"pkg:maven/com.h2database/h2@2.1.210","referenceType":"purl"}]},{"SPDXID":"SPDXRef-maven-com.h2database-h2-2.1.212","name":"maven:com.h2database:h2","versionInfo":"2.1.212","downloadLocation":"NOASSERTION","filesAnalyzed":false,"licenseConcluded":"NOASSERTION","licenseDeclared":"NOASSERTION","supplier":"NOASSERTION","externalRefs":[{"referenceCategory":"PACKAGE-MANAGER","referenceLocator":"pkg:maven/com.h2database/h2@2.1.212","referenceType":"purl"}]},{"SPDXID":"SPDXRef-maven-com.h2database-h2-2.1.214","name":"maven:com.h2database:h2","versionInfo":"2.1.214","downloadLocation":"NOASSERTION","filesAnalyzed":false,"licenseConcluded":"MPL-2.0 OR EPL-1.0","licenseDeclared":"NOASSERTION","supplier":"NOASSERTION","externalRefs":[{"referenceCategory":"PACKAGE-MANAGER","referenceLocator":"pkg:maven/com.h2database/h2@2.1.214","referenceType":"purl"}]},{"SPDXID":"SPDXRef-maven-com.microsoft.sqlserver-mssql-jdbc-10.2.0.jre8","name":"maven:com.microsoft.sqlserver:mssql-jdbc","versionInfo":"10.2.0.jre8","downloadLocation":"NOASSERTION","filesAnalyzed":false,"licenseConcluded":"MIT","licenseDeclared":"NOASSERTION","supplier":"NOASSERTION","externalRefs":[{"referenceCategory":"PACKAGE-MANAGER","referenceLocator":"pkg:maven/com.microsoft.sqlserver/mssql-jdbc@10.2.0.jre8","referenceType":"purl"}]},{"SPDXID":"SPDXRef-maven-com.microsoft.sqlserver-mssql-jdbc-11.1.1.jre8-preview","name":"maven:com.microsoft.sqlserver:mssql-jdbc","versionInfo":"11.1.1.jre8-preview","downloadLocation":"NOASSERTION","filesAnalyzed":false,"licenseConcluded":"MIT","licenseDeclared":"NOASSERTION","supplier":"NOASSERTION","externalRefs":[{"referenceCategory":"PACKAGE-MANAGER","referenceLocator":"pkg:maven/com.microsoft.sqlserver/mssql-jdbc@11.1.1.jre8-preview","referenceType":"purl"}]},{"SPDXID":"SPDXRef-maven-com.microsoft.sqlserver-mssql-jdbc-11.1.2.jre8-preview","name":"maven:com.microsoft.sqlserver:mssql-jdbc","versionInfo":"11.1.2.jre8-preview","downloadLocation":"NOASSERTION","filesAnalyzed":false,"licenseConcluded":"MIT","licenseDeclared":"NOASSERTION","supplier":"NOASSERTION","externalRefs":[{"referenceCategory":"PACKAGE-MANAGER","referenceLocator":"pkg:maven/com.microsoft.sqlserver/mssql-jdbc@11.1.2.jre8-preview","referenceType":"purl"}]},{"SPDXID":"SPDXRef-maven-com.microsoft.sqlserver-mssql-jdbc-11.2.0.jre8","name":"maven:com.microsoft.sqlserver:mssql-jdbc","versionInfo":"11.2.0.jre8","downloadLocation":"NOASSERTION","filesAnalyzed":false,"licenseConcluded":"MIT","licenseDeclared":"NOASSERTION","supplier":"NOASSERTION","externalRefs":[{"referenceCategory":"PACKAGE-MANAGER","referenceLocator":"pkg:maven/com.microsoft.sqlserver/mssql-jdbc@11.2.0.jre8","referenceType":"purl"}]},{"SPDXID":"SPDXRef-maven-com.microsoft.sqlserver-mssql-jdbc-9.4.1.jre8","name":"maven:com.microsoft.sqlserver:mssql-jdbc","versionInfo":"9.4.1.jre8","downloadLocation":"NOASSERTION","filesAnalyzed":false,"licenseConcluded":"MIT","licenseDeclared":"NOASSERTION","supplier":"NOASSERTION","externalRefs":[{"referenceCategory":"PACKAGE-MANAGER","referenceLocator":"pkg:maven/com.microsoft.sqlserver/mssql-jdbc@9.4.1.jre8","referenceType":"purl"}]},{"SPDXID":"SPDXRef-maven-com.mysql-mysql-connector-j-8.0.31","name":"maven:com.mysql:mysql-connector-j","versionInfo":"8.0.31","downloadLocation":"NOASSERTION","filesAnalyzed":false,"licenseConcluded":"EPL-1.0 AND GPL-1.0-or-later AND GPL-2.0-only AND GPL-2.0-only OR LGPL-2.1-only AND GPL-3.0-only AND LGPL-2.0-or-later AND LGPL-2.1-only AND LGPL-3.0-or-later OR GPL-2.0-or-later AND NOASSERTION","licenseDeclared":"NOASSERTION","supplier":"NOASSERTION","externalRefs":[{"referenceCategory":"PACKAGE-MANAGER","referenceLocator":"pkg:maven/com.mysql/mysql-connector-j@8.0.31","referenceType":"purl"}]},{"SPDXID":"SPDXRef-maven-com.mysql-mysql-connector-j-8.0.32","name":"maven:com.mysql:mysql-connector-j","versionInfo":"8.0.32","downloadLocation":"NOASSERTION","filesAnalyzed":false,"licenseConcluded":"EPL-1.0 AND GPL-1.0-or-later AND GPL-2.0-only AND GPL-2.0-only OR LGPL-2.1-only AND GPL-3.0-only AND LGPL-2.0-or-later AND LGPL-2.1-only AND LGPL-3.0-or-later OR GPL-2.0-or-later AND NOASSERTION","licenseDeclared":"NOASSERTION","supplier":"NOASSERTION","externalRefs":[{"referenceCategory":"PACKAGE-MANAGER","referenceLocator":"pkg:maven/com.mysql/mysql-connector-j@8.0.32","referenceType":"purl"}]},{"SPDXID":"SPDXRef-maven-com.mysql-mysql-connector-j-8.0.33","name":"maven:com.mysql:mysql-connector-j","versionInfo":"8.0.33","downloadLocation":"NOASSERTION","filesAnalyzed":false,"licenseConcluded":"NOASSERTION","licenseDeclared":"NOASSERTION","supplier":"NOASSERTION","externalRefs":[{"referenceCategory":"PACKAGE-MANAGER","referenceLocator":"pkg:maven/com.mysql/mysql-connector-j@8.0.33","referenceType":"purl"}]},{"SPDXID":"SPDXRef-maven-commons-logging-commons-logging-1.2","name":"maven:commons-logging:commons-logging","versionInfo":"1.2","downloadLocation":"NOASSERTION","filesAnalyzed":false,"licenseConcluded":"Apache-2.0","licenseDeclared":"NOASSERTION","supplier":"NOASSERTION","externalRefs":[{"referenceCategory":"PACKAGE-MANAGER","referenceLocator":"pkg:maven/commons-logging/commons-logging@1.2","referenceType":"purl"}]},{"SPDXID":"SPDXRef-maven-eu.codearte.catch-exception-catch-exception-2.0","name":"maven:eu.codearte.catch-exception:catch-exception","versionInfo":"2.0","downloadLocation":"NOASSERTION","filesAnalyzed":false,"licenseConcluded":"Apache-2.0","licenseDeclared":"NOASSERTION","supplier":"NOASSERTION","externalRefs":[{"referenceCategory":"PACKAGE-MANAGER","referenceLocator":"pkg:maven/eu.codearte.catch-exception/catch-exception@2.0","referenceType":"purl"}]},{"SPDXID":"SPDXRef-maven-javax.transaction-javax.transaction-api-1.3","name":"maven:javax.transaction:javax.transaction-api","versionInfo":"1.3","downloadLocation":"NOASSERTION","filesAnalyzed":false,"licenseConcluded":"NOASSERTION","licenseDeclared":"NOASSERTION","supplier":"NOASSERTION","externalRefs":[{"referenceCategory":"PACKAGE-MANAGER","referenceLocator":"pkg:maven/javax.transaction/javax.transaction-api@1.3","referenceType":"purl"}]},{"SPDXID":"SPDXRef-maven-log4j-log4j-1.2.17","name":"maven:log4j:log4j","versionInfo":"1.2.17","downloadLocation":"NOASSERTION","filesAnalyzed":false,"licenseConcluded":"Apache-2.0","licenseDeclared":"NOASSERTION","supplier":"NOASSERTION","externalRefs":[{"referenceCategory":"PACKAGE-MANAGER","referenceLocator":"pkg:maven/log4j/log4j@1.2.17","referenceType":"purl"}]},{"SPDXID":"SPDXRef-maven-mysql-mysql-connector-java-8.0.28","name":"maven:mysql:mysql-connector-java","versionInfo":"8.0.28","downloadLocation":"NOASSERTION","filesAnalyzed":false,"licenseConcluded":"NOASSERTION","licenseDeclared":"NOASSERTION","supplier":"NOASSERTION","externalRefs":[{"referenceCategory":"PACKAGE-MANAGER","referenceLocator":"pkg:maven/mysql/mysql-connector-java@8.0.28","referenceType":"purl"}]},{"SPDXID":"SPDXRef-maven-mysql-mysql-connector-java-8.0.29","name":"maven:mysql:mysql-connector-java","versionInfo":"8.0.29","downloadLocation":"NOASSERTION","filesAnalyzed":false,"licenseConcluded":"NOASSERTION","licenseDeclared":"NOASSERTION","supplier":"NOASSERTION","externalRefs":[{"referenceCategory":"PACKAGE-MANAGER","referenceLocator":"pkg:maven/mysql/mysql-connector-java@8.0.29","referenceType":"purl"}]},{"SPDXID":"SPDXRef-maven-mysql-mysql-connector-java-8.0.30","name":"maven:mysql:mysql-connector-java","versionInfo":"8.0.30","downloadLocation":"NOASSERTION","filesAnalyzed":false,"licenseConcluded":"NOASSERTION","licenseDeclared":"NOASSERTION","supplier":"NOASSERTION","externalRefs":[{"referenceCategory":"PACKAGE-MANAGER","referenceLocator":"pkg:maven/mysql/mysql-connector-java@8.0.30","referenceType":"purl"}]},{"SPDXID":"SPDXRef-maven-mysql-mysql-connector-java-8.0.31","name":"maven:mysql:mysql-connector-java","versionInfo":"8.0.31","downloadLocation":"NOASSERTION","filesAnalyzed":false,"licenseConcluded":"NOASSERTION","licenseDeclared":"NOASSERTION","supplier":"NOASSERTION","externalRefs":[{"referenceCategory":"PACKAGE-MANAGER","referenceLocator":"pkg:maven/mysql/mysql-connector-java@8.0.31","referenceType":"purl"}]},{"SPDXID":"SPDXRef-maven-net.revelc.code-impsort-maven-plugin","name":"maven:net.revelc.code:impsort-maven-plugin","versionInfo":"","downloadLocation":"NOASSERTION","filesAnalyzed":false,"licenseConcluded":"NOASSERTION","licenseDeclared":"NOASSERTION","supplier":"NOASSERTION"},{"SPDXID":"SPDXRef-maven-ognl-ognl-3.3.2","name":"maven:ognl:ognl","versionInfo":"3.3.2","downloadLocation":"NOASSERTION","filesAnalyzed":false,"licenseConcluded":"Apache-2.0","licenseDeclared":"NOASSERTION","supplier":"NOASSERTION","externalRefs":[{"referenceCategory":"PACKAGE-MANAGER","referenceLocator":"pkg:maven/ognl/ognl@3.3.2","referenceType":"purl"}]},{"SPDXID":"SPDXRef-maven-ognl-ognl-3.3.3","name":"maven:ognl:ognl","versionInfo":"3.3.3","downloadLocation":"NOASSERTION","filesAnalyzed":false,"licenseConcluded":"Apache-2.0","licenseDeclared":"NOASSERTION","supplier":"NOASSERTION","externalRefs":[{"referenceCategory":"PACKAGE-MANAGER","referenceLocator":"pkg:maven/ognl/ognl@3.3.3","referenceType":"purl"}]},{"SPDXID":"SPDXRef-maven-ognl-ognl-3.3.4","name":"maven:ognl:ognl","versionInfo":"3.3.4","downloadLocation":"NOASSERTION","filesAnalyzed":false,"licenseConcluded":"Apache-2.0","licenseDeclared":"NOASSERTION","supplier":"NOASSERTION","externalRefs":[{"referenceCategory":"PACKAGE-MANAGER","referenceLocator":"pkg:maven/ognl/ognl@3.3.4","referenceType":"purl"}]},{"SPDXID":"SPDXRef-maven-org.apache.commons-commons-dbcp2-2.6.0","name":"maven:org.apache.commons:commons-dbcp2","versionInfo":"2.6.0","downloadLocation":"NOASSERTION","filesAnalyzed":false,"licenseConcluded":"Apache-2.0","licenseDeclared":"NOASSERTION","supplier":"NOASSERTION","externalRefs":[{"referenceCategory":"PACKAGE-MANAGER","referenceLocator":"pkg:maven/org.apache.commons/commons-dbcp2@2.6.0","referenceType":"purl"}]},{"SPDXID":"SPDXRef-maven-org.apache.derby-derby-10.14.2.0","name":"maven:org.apache.derby:derby","versionInfo":"10.14.2.0","downloadLocation":"NOASSERTION","filesAnalyzed":false,"licenseConcluded":"Apache-2.0","licenseDeclared":"NOASSERTION","supplier":"NOASSERTION","externalRefs":[{"referenceCategory":"PACKAGE-MANAGER","referenceLocator":"pkg:maven/org.apache.derby/derby@10.14.2.0","referenceType":"purl"}]},{"SPDXID":"SPDXRef-maven-org.apache.derby-derby-10.15.2.0","name":"maven:org.apache.derby:derby","versionInfo":"10.15.2.0","downloadLocation":"NOASSERTION","filesAnalyzed":false,"licenseConcluded":"Apache-2.0","licenseDeclared":"NOASSERTION","supplier":"NOASSERTION","externalRefs":[{"referenceCategory":"PACKAGE-MANAGER","referenceLocator":"pkg:maven/org.apache.derby/derby@10.15.2.0","referenceType":"purl"}]},{"SPDXID":"SPDXRef-maven-org.apache.derby-derbyoptionaltools-10.15.2.0","name":"maven:org.apache.derby:derbyoptionaltools","versionInfo":"10.15.2.0","downloadLocation":"NOASSERTION","filesAnalyzed":false,"licenseConcluded":"NOASSERTION","licenseDeclared":"NOASSERTION","supplier":"NOASSERTION","externalRefs":[{"referenceCategory":"PACKAGE-MANAGER","referenceLocator":"pkg:maven/org.apache.derby/derbyoptionaltools@10.15.2.0","referenceType":"purl"}]},{"SPDXID":"SPDXRef-maven-org.apache.derby-derbyshared-10.15.2.0","name":"maven:org.apache.derby:derbyshared","versionInfo":"10.15.2.0","downloadLocation":"NOASSERTION","filesAnalyzed":false,"licenseConcluded":"Apache-2.0","licenseDeclared":"NOASSERTION","supplier":"NOASSERTION","externalRefs":[{"referenceCategory":"PACKAGE-MANAGER","referenceLocator":"pkg:maven/org.apache.derby/derbyshared@10.15.2.0","referenceType":"purl"}]},{"SPDXID":"SPDXRef-maven-org.apache.logging.log4j-log4j-api-2.17.1","name":"maven:org.apache.logging.log4j:log4j-api","versionInfo":"2.17.1","downloadLocation":"NOASSERTION","filesAnalyzed":false,"licenseConcluded":"Apache-2.0","licenseDeclared":"NOASSERTION","supplier":"NOASSERTION","externalRefs":[{"referenceCategory":"PACKAGE-MANAGER","referenceLocator":"pkg:maven/org.apache.logging.log4j/log4j-api@2.17.1","referenceType":"purl"}]},{"SPDXID":"SPDXRef-maven-org.apache.logging.log4j-log4j-api-2.17.2","name":"maven:org.apache.logging.log4j:log4j-api","versionInfo":"2.17.2","downloadLocation":"NOASSERTION","filesAnalyzed":false,"licenseConcluded":"Apache-2.0","licenseDeclared":"NOASSERTION","supplier":"NOASSERTION","externalRefs":[{"referenceCategory":"PACKAGE-MANAGER","referenceLocator":"pkg:maven/org.apache.logging.log4j/log4j-api@2.17.2","referenceType":"purl"}]},{"SPDXID":"SPDXRef-maven-org.apache.logging.log4j-log4j-api-2.18.0","name":"maven:org.apache.logging.log4j:log4j-api","versionInfo":"2.18.0","downloadLocation":"NOASSERTION","filesAnalyzed":false,"licenseConcluded":"Apache-2.0","licenseDeclared":"NOASSERTION","supplier":"NOASSERTION","externalRefs":[{"referenceCategory":"PACKAGE-MANAGER","referenceLocator":"pkg:maven/org.apache.logging.log4j/log4j-api@2.18.0","referenceType":"purl"}]},{"SPDXID":"SPDXRef-maven-org.apache.logging.log4j-log4j-api-2.19.0","name":"maven:org.apache.logging.log4j:log4j-api","versionInfo":"2.19.0","downloadLocation":"NOASSERTION","filesAnalyzed":false,"licenseConcluded":"Apache-2.0","licenseDeclared":"NOASSERTION","supplier":"NOASSERTION","externalRefs":[{"referenceCategory":"PACKAGE-MANAGER","referenceLocator":"pkg:maven/org.apache.logging.log4j/log4j-api@2.19.0","referenceType":"purl"}]},{"SPDXID":"SPDXRef-maven-org.apache.logging.log4j-log4j-api-2.20.0","name":"maven:org.apache.logging.log4j:log4j-api","versionInfo":"2.20.0","downloadLocation":"NOASSERTION","filesAnalyzed":false,"licenseConcluded":"Apache-2.0","licenseDeclared":"NOASSERTION","supplier":"NOASSERTION","externalRefs":[{"referenceCategory":"PACKAGE-MANAGER","referenceLocator":"pkg:maven/org.apache.logging.log4j/log4j-api@2.20.0","referenceType":"purl"}]},{"SPDXID":"SPDXRef-maven-org.apache.logging.log4j-log4j-core-2.17.1","name":"maven:org.apache.logging.log4j:log4j-core","versionInfo":"2.17.1","downloadLocation":"NOASSERTION","filesAnalyzed":false,"licenseConcluded":"Apache-2.0","licenseDeclared":"NOASSERTION","supplier":"NOASSERTION","externalRefs":[{"referenceCategory":"PACKAGE-MANAGER","referenceLocator":"pkg:maven/org.apache.logging.log4j/log4j-core@2.17.1","referenceType":"purl"}]},{"SPDXID":"SPDXRef-maven-org.apache.logging.log4j-log4j-core-2.17.2","name":"maven:org.apache.logging.log4j:log4j-core","versionInfo":"2.17.2","downloadLocation":"NOASSERTION","filesAnalyzed":false,"licenseConcluded":"Apache-2.0","licenseDeclared":"NOASSERTION","supplier":"NOASSERTION","externalRefs":[{"referenceCategory":"PACKAGE-MANAGER","referenceLocator":"pkg:maven/org.apache.logging.log4j/log4j-core@2.17.2","referenceType":"purl"}]},{"SPDXID":"SPDXRef-maven-org.apache.logging.log4j-log4j-core-2.18.0","name":"maven:org.apache.logging.log4j:log4j-core","versionInfo":"2.18.0","downloadLocation":"NOASSERTION","filesAnalyzed":false,"licenseConcluded":"Apache-2.0","licenseDeclared":"NOASSERTION","supplier":"NOASSERTION","externalRefs":[{"referenceCategory":"PACKAGE-MANAGER","referenceLocator":"pkg:maven/org.apache.logging.log4j/log4j-core@2.18.0","referenceType":"purl"}]},{"SPDXID":"SPDXRef-maven-org.apache.logging.log4j-log4j-core-2.19.0","name":"maven:org.apache.logging.log4j:log4j-core","versionInfo":"2.19.0","downloadLocation":"NOASSERTION","filesAnalyzed":false,"licenseConcluded":"Apache-2.0","licenseDeclared":"NOASSERTION","supplier":"NOASSERTION","externalRefs":[{"referenceCategory":"PACKAGE-MANAGER","referenceLocator":"pkg:maven/org.apache.logging.log4j/log4j-core@2.19.0","referenceType":"purl"}]},{"SPDXID":"SPDXRef-maven-org.apache.logging.log4j-log4j-core-2.20.0","name":"maven:org.apache.logging.log4j:log4j-core","versionInfo":"2.20.0","downloadLocation":"NOASSERTION","filesAnalyzed":false,"licenseConcluded":"Apache-2.0","licenseDeclared":"NOASSERTION","supplier":"NOASSERTION","externalRefs":[{"referenceCategory":"PACKAGE-MANAGER","referenceLocator":"pkg:maven/org.apache.logging.log4j/log4j-core@2.20.0","referenceType":"purl"}]},{"SPDXID":"SPDXRef-maven-org.apache.maven.plugins-maven-compiler-plugin","name":"maven:org.apache.maven.plugins:maven-compiler-plugin","versionInfo":"","downloadLocation":"NOASSERTION","filesAnalyzed":false,"licenseConcluded":"NOASSERTION","licenseDeclared":"NOASSERTION","supplier":"NOASSERTION"},{"SPDXID":"SPDXRef-maven-org.apache.maven.plugins-maven-enforcer-plugin","name":"maven:org.apache.maven.plugins:maven-enforcer-plugin","versionInfo":"","downloadLocation":"NOASSERTION","filesAnalyzed":false,"licenseConcluded":"NOASSERTION","licenseDeclared":"NOASSERTION","supplier":"NOASSERTION"},{"SPDXID":"SPDXRef-maven-org.apache.maven.plugins-maven-pdf-plugin","name":"maven:org.apache.maven.plugins:maven-pdf-plugin","versionInfo":"","downloadLocation":"NOASSERTION","filesAnalyzed":false,"licenseConcluded":"NOASSERTION","licenseDeclared":"NOASSERTION","supplier":"NOASSERTION"},{"SPDXID":"SPDXRef-maven-org.apache.maven.plugins-maven-shade-plugin","name":"maven:org.apache.maven.plugins:maven-shade-plugin","versionInfo":"","downloadLocation":"NOASSERTION","filesAnalyzed":false,"licenseConcluded":"NOASSERTION","licenseDeclared":"NOASSERTION","supplier":"NOASSERTION"},{"SPDXID":"SPDXRef-maven-org.apache.maven.plugins-maven-site-plugin","name":"maven:org.apache.maven.plugins:maven-site-plugin","versionInfo":"","downloadLocation":"NOASSERTION","filesAnalyzed":false,"licenseConcluded":"NOASSERTION","licenseDeclared":"NOASSERTION","supplier":"NOASSERTION"},{"SPDXID":"SPDXRef-maven-org.apache.maven.plugins-maven-surefire-plugin","name":"maven:org.apache.maven.plugins:maven-surefire-plugin","versionInfo":"","downloadLocation":"NOASSERTION","filesAnalyzed":false,"licenseConcluded":"NOASSERTION","licenseDeclared":"NOASSERTION","supplier":"NOASSERTION"},{"SPDXID":"SPDXRef-maven-org.apache.velocity-velocity-1.7","name":"maven:org.apache.velocity:velocity","versionInfo":"1.7","downloadLocation":"NOASSERTION","filesAnalyzed":false,"licenseConcluded":"Apache-2.0","licenseDeclared":"NOASSERTION","supplier":"NOASSERTION","externalRefs":[{"referenceCategory":"PACKAGE-MANAGER","referenceLocator":"pkg:maven/org.apache.velocity/velocity@1.7","referenceType":"purl"}]},{"SPDXID":"SPDXRef-maven-org.apache.velocity-velocity-engine-core-2.3","name":"maven:org.apache.velocity:velocity-engine-core","versionInfo":"2.3","downloadLocation":"NOASSERTION","filesAnalyzed":false,"licenseConcluded":"Apache-2.0","licenseDeclared":"NOASSERTION","supplier":"NOASSERTION","externalRefs":[{"referenceCategory":"PACKAGE-MANAGER","referenceLocator":"pkg:maven/org.apache.velocity/velocity-engine-core@2.3","referenceType":"purl"}]},{"SPDXID":"SPDXRef-maven-org.assertj-assertj-core-3.22.0","name":"maven:org.assertj:assertj-core","versionInfo":"3.22.0","downloadLocation":"NOASSERTION","filesAnalyzed":false,"licenseConcluded":"Apache-2.0","licenseDeclared":"NOASSERTION","supplier":"NOASSERTION","externalRefs":[{"referenceCategory":"PACKAGE-MANAGER","referenceLocator":"pkg:maven/org.assertj/assertj-core@3.22.0","referenceType":"purl"}]},{"SPDXID":"SPDXRef-maven-org.assertj-assertj-core-3.23.0","name":"maven:org.assertj:assertj-core","versionInfo":"3.23.0","downloadLocation":"NOASSERTION","filesAnalyzed":false,"licenseConcluded":"Apache-2.0","licenseDeclared":"NOASSERTION","supplier":"NOASSERTION","externalRefs":[{"referenceCategory":"PACKAGE-MANAGER","referenceLocator":"pkg:maven/org.assertj/assertj-core@3.23.0","referenceType":"purl"}]},{"SPDXID":"SPDXRef-maven-org.assertj-assertj-core-3.23.1","name":"maven:org.assertj:assertj-core","versionInfo":"3.23.1","downloadLocation":"NOASSERTION","filesAnalyzed":false,"licenseConcluded":"Apache-2.0","licenseDeclared":"NOASSERTION","supplier":"NOASSERTION","externalRefs":[{"referenceCategory":"PACKAGE-MANAGER","referenceLocator":"pkg:maven/org.assertj/assertj-core@3.23.1","referenceType":"purl"}]},{"SPDXID":"SPDXRef-maven-org.assertj-assertj-core-3.24.1","name":"maven:org.assertj:assertj-core","versionInfo":"3.24.1","downloadLocation":"NOASSERTION","filesAnalyzed":false,"licenseConcluded":"Apache-2.0","licenseDeclared":"NOASSERTION","supplier":"NOASSERTION","externalRefs":[{"referenceCategory":"PACKAGE-MANAGER","referenceLocator":"pkg:maven/org.assertj/assertj-core@3.24.1","referenceType":"purl"}]},{"SPDXID":"SPDXRef-maven-org.assertj-assertj-core-3.24.2","name":"maven:org.assertj:assertj-core","versionInfo":"3.24.2","downloadLocation":"NOASSERTION","filesAnalyzed":false,"licenseConcluded":"Apache-2.0","licenseDeclared":"NOASSERTION","supplier":"NOASSERTION","externalRefs":[{"referenceCategory":"PACKAGE-MANAGER","referenceLocator":"pkg:maven/org.assertj/assertj-core@3.24.2","referenceType":"purl"}]},{"SPDXID":"SPDXRef-maven-org.codehaus.mojo-animal-sniffer-maven-plugin","name":"maven:org.codehaus.mojo:animal-sniffer-maven-plugin","versionInfo":"","downloadLocation":"NOASSERTION","filesAnalyzed":false,"licenseConcluded":"NOASSERTION","licenseDeclared":"NOASSERTION","supplier":"NOASSERTION"},{"SPDXID":"SPDXRef-maven-org.hsqldb-hsqldb-2.5.2","name":"maven:org.hsqldb:hsqldb","versionInfo":"2.5.2","downloadLocation":"NOASSERTION","filesAnalyzed":false,"licenseConcluded":"NOASSERTION","licenseDeclared":"NOASSERTION","supplier":"NOASSERTION","externalRefs":[{"referenceCategory":"PACKAGE-MANAGER","referenceLocator":"pkg:maven/org.hsqldb/hsqldb@2.5.2","referenceType":"purl"}]},{"SPDXID":"SPDXRef-maven-org.hsqldb-hsqldb-2.6.1","name":"maven:org.hsqldb:hsqldb","versionInfo":"2.6.1","downloadLocation":"NOASSERTION","filesAnalyzed":false,"licenseConcluded":"NOASSERTION","licenseDeclared":"NOASSERTION","supplier":"NOASSERTION","externalRefs":[{"referenceCategory":"PACKAGE-MANAGER","referenceLocator":"pkg:maven/org.hsqldb/hsqldb@2.6.1","referenceType":"purl"}]},{"SPDXID":"SPDXRef-maven-org.jacoco-jacoco-maven-plugin","name":"maven:org.jacoco:jacoco-maven-plugin","versionInfo":"","downloadLocation":"NOASSERTION","filesAnalyzed":false,"licenseConcluded":"NOASSERTION","licenseDeclared":"NOASSERTION","supplier":"NOASSERTION"},{"SPDXID":"SPDXRef-maven-org.javassist-javassist-3.28.0-GA","name":"maven:org.javassist:javassist","versionInfo":"3.28.0-GA","downloadLocation":"NOASSERTION","filesAnalyzed":false,"licenseConcluded":"LGPL-2.1","licenseDeclared":"NOASSERTION","supplier":"NOASSERTION","externalRefs":[{"referenceCategory":"PACKAGE-MANAGER","referenceLocator":"pkg:maven/org.javassist/javassist@3.28.0-GA","referenceType":"purl"}]},{"SPDXID":"SPDXRef-maven-org.javassist-javassist-3.29.0-GA","name":"maven:org.javassist:javassist","versionInfo":"3.29.0-GA","downloadLocation":"NOASSERTION","filesAnalyzed":false,"licenseConcluded":"LGPL-2.1 OR Apache-2.0","licenseDeclared":"NOASSERTION","supplier":"NOASSERTION","externalRefs":[{"referenceCategory":"PACKAGE-MANAGER","referenceLocator":"pkg:maven/org.javassist/javassist@3.29.0-GA","referenceType":"purl"}]},{"SPDXID":"SPDXRef-maven-org.javassist-javassist-3.29.1-GA","name":"maven:org.javassist:javassist","versionInfo":"3.29.1-GA","downloadLocation":"NOASSERTION","filesAnalyzed":false,"licenseConcluded":"LGPL-2.1 OR Apache-2.0","licenseDeclared":"NOASSERTION","supplier":"NOASSERTION","externalRefs":[{"referenceCategory":"PACKAGE-MANAGER","referenceLocator":"pkg:maven/org.javassist/javassist@3.29.1-GA","referenceType":"purl"}]},{"SPDXID":"SPDXRef-maven-org.javassist-javassist-3.29.2-GA","name":"maven:org.javassist:javassist","versionInfo":"3.29.2-GA","downloadLocation":"NOASSERTION","filesAnalyzed":false,"licenseConcluded":"LGPL-2.1 OR Apache-2.0","licenseDeclared":"NOASSERTION","supplier":"NOASSERTION","externalRefs":[{"referenceCategory":"PACKAGE-MANAGER","referenceLocator":"pkg:maven/org.javassist/javassist@3.29.2-GA","referenceType":"purl"}]},{"SPDXID":"SPDXRef-maven-org.junit.jupiter-junit-jupiter-engine-5.8.2","name":"maven:org.junit.jupiter:junit-jupiter-engine","versionInfo":"5.8.2","downloadLocation":"NOASSERTION","filesAnalyzed":false,"licenseConcluded":"NOASSERTION","licenseDeclared":"NOASSERTION","supplier":"NOASSERTION","externalRefs":[{"referenceCategory":"PACKAGE-MANAGER","referenceLocator":"pkg:maven/org.junit.jupiter/junit-jupiter-engine@5.8.2","referenceType":"purl"}]},{"SPDXID":"SPDXRef-maven-org.junit.jupiter-junit-jupiter-engine-5.9.0","name":"maven:org.junit.jupiter:junit-jupiter-engine","versionInfo":"5.9.0","downloadLocation":"NOASSERTION","filesAnalyzed":false,"licenseConcluded":"NOASSERTION","licenseDeclared":"NOASSERTION","supplier":"NOASSERTION","externalRefs":[{"referenceCategory":"PACKAGE-MANAGER","referenceLocator":"pkg:maven/org.junit.jupiter/junit-jupiter-engine@5.9.0","referenceType":"purl"}]},{"SPDXID":"SPDXRef-maven-org.junit.jupiter-junit-jupiter-engine-5.9.1","name":"maven:org.junit.jupiter:junit-jupiter-engine","versionInfo":"5.9.1","downloadLocation":"NOASSERTION","filesAnalyzed":false,"licenseConcluded":"NOASSERTION","licenseDeclared":"NOASSERTION","supplier":"NOASSERTION","externalRefs":[{"referenceCategory":"PACKAGE-MANAGER","referenceLocator":"pkg:maven/org.junit.jupiter/junit-jupiter-engine@5.9.1","referenceType":"purl"}]},{"SPDXID":"SPDXRef-maven-org.junit.jupiter-junit-jupiter-engine-5.9.2","name":"maven:org.junit.jupiter:junit-jupiter-engine","versionInfo":"5.9.2","downloadLocation":"NOASSERTION","filesAnalyzed":false,"licenseConcluded":"NOASSERTION","licenseDeclared":"NOASSERTION","supplier":"NOASSERTION","externalRefs":[{"referenceCategory":"PACKAGE-MANAGER","referenceLocator":"pkg:maven/org.junit.jupiter/junit-jupiter-engine@5.9.2","referenceType":"purl"}]},{"SPDXID":"SPDXRef-maven-org.junit.jupiter-junit-jupiter-engine-5.9.3","name":"maven:org.junit.jupiter:junit-jupiter-engine","versionInfo":"5.9.3","downloadLocation":"NOASSERTION","filesAnalyzed":false,"licenseConcluded":"NOASSERTION","licenseDeclared":"NOASSERTION","supplier":"NOASSERTION","externalRefs":[{"referenceCategory":"PACKAGE-MANAGER","referenceLocator":"pkg:maven/org.junit.jupiter/junit-jupiter-engine@5.9.3","referenceType":"purl"}]},{"SPDXID":"SPDXRef-maven-org.junit.jupiter-junit-jupiter-params-5.7.1","name":"maven:org.junit.jupiter:junit-jupiter-params","versionInfo":"5.7.1","downloadLocation":"NOASSERTION","filesAnalyzed":false,"licenseConcluded":"NOASSERTION","licenseDeclared":"NOASSERTION","supplier":"NOASSERTION","externalRefs":[{"referenceCategory":"PACKAGE-MANAGER","referenceLocator":"pkg:maven/org.junit.jupiter/junit-jupiter-params@5.7.1","referenceType":"purl"}]},{"SPDXID":"SPDXRef-maven-org.junit.jupiter-junit-jupiter-params-5.9.0","name":"maven:org.junit.jupiter:junit-jupiter-params","versionInfo":"5.9.0","downloadLocation":"NOASSERTION","filesAnalyzed":false,"licenseConcluded":"NOASSERTION","licenseDeclared":"NOASSERTION","supplier":"NOASSERTION","externalRefs":[{"referenceCategory":"PACKAGE-MANAGER","referenceLocator":"pkg:maven/org.junit.jupiter/junit-jupiter-params@5.9.0","referenceType":"purl"}]},{"SPDXID":"SPDXRef-maven-org.junit.jupiter-junit-jupiter-params-5.9.1","name":"maven:org.junit.jupiter:junit-jupiter-params","versionInfo":"5.9.1","downloadLocation":"NOASSERTION","filesAnalyzed":false,"licenseConcluded":"NOASSERTION","licenseDeclared":"NOASSERTION","supplier":"NOASSERTION","externalRefs":[{"referenceCategory":"PACKAGE-MANAGER","referenceLocator":"pkg:maven/org.junit.jupiter/junit-jupiter-params@5.9.1","referenceType":"purl"}]},{"SPDXID":"SPDXRef-maven-org.junit.jupiter-junit-jupiter-params-5.9.2","name":"maven:org.junit.jupiter:junit-jupiter-params","versionInfo":"5.9.2","downloadLocation":"NOASSERTION","filesAnalyzed":false,"licenseConcluded":"NOASSERTION","licenseDeclared":"NOASSERTION","supplier":"NOASSERTION","externalRefs":[{"referenceCategory":"PACKAGE-MANAGER","referenceLocator":"pkg:maven/org.junit.jupiter/junit-jupiter-params@5.9.2","referenceType":"purl"}]},{"SPDXID":"SPDXRef-maven-org.junit.jupiter-junit-jupiter-params-5.9.3","name":"maven:org.junit.jupiter:junit-jupiter-params","versionInfo":"5.9.3","downloadLocation":"NOASSERTION","filesAnalyzed":false,"licenseConcluded":"NOASSERTION","licenseDeclared":"NOASSERTION","supplier":"NOASSERTION","externalRefs":[{"referenceCategory":"PACKAGE-MANAGER","referenceLocator":"pkg:maven/org.junit.jupiter/junit-jupiter-params@5.9.3","referenceType":"purl"}]},{"SPDXID":"SPDXRef-maven-org.junit.vintage-junit-vintage-engine-5.3.2","name":"maven:org.junit.vintage:junit-vintage-engine","versionInfo":"5.3.2","downloadLocation":"NOASSERTION","filesAnalyzed":false,"licenseConcluded":"NOASSERTION","licenseDeclared":"NOASSERTION","supplier":"NOASSERTION","externalRefs":[{"referenceCategory":"PACKAGE-MANAGER","referenceLocator":"pkg:maven/org.junit.vintage/junit-vintage-engine@5.3.2","referenceType":"purl"}]},{"SPDXID":"SPDXRef-maven-org.mockito-mockito-core-4.10.0","name":"maven:org.mockito:mockito-core","versionInfo":"4.10.0","downloadLocation":"NOASSERTION","filesAnalyzed":false,"licenseConcluded":"MIT","licenseDeclared":"NOASSERTION","supplier":"NOASSERTION","externalRefs":[{"referenceCategory":"PACKAGE-MANAGER","referenceLocator":"pkg:maven/org.mockito/mockito-core@4.10.0","referenceType":"purl"}]},{"SPDXID":"SPDXRef-maven-org.mockito-mockito-core-4.11.0","name":"maven:org.mockito:mockito-core","versionInfo":"4.11.0","downloadLocation":"NOASSERTION","filesAnalyzed":false,"licenseConcluded":"MIT","licenseDeclared":"NOASSERTION","supplier":"NOASSERTION","externalRefs":[{"referenceCategory":"PACKAGE-MANAGER","referenceLocator":"pkg:maven/org.mockito/mockito-core@4.11.0","referenceType":"purl"}]},{"SPDXID":"SPDXRef-maven-org.mockito-mockito-core-4.3.1","name":"maven:org.mockito:mockito-core","versionInfo":"4.3.1","downloadLocation":"NOASSERTION","filesAnalyzed":false,"licenseConcluded":"MIT","licenseDeclared":"NOASSERTION","supplier":"NOASSERTION","externalRefs":[{"referenceCategory":"PACKAGE-MANAGER","referenceLocator":"pkg:maven/org.mockito/mockito-core@4.3.1","referenceType":"purl"}]},{"SPDXID":"SPDXRef-maven-org.mockito-mockito-core-4.4.0","name":"maven:org.mockito:mockito-core","versionInfo":"4.4.0","downloadLocation":"NOASSERTION","filesAnalyzed":false,"licenseConcluded":"MIT","licenseDeclared":"NOASSERTION","supplier":"NOASSERTION","externalRefs":[{"referenceCategory":"PACKAGE-MANAGER","referenceLocator":"pkg:maven/org.mockito/mockito-core@4.4.0","referenceType":"purl"}]},{"SPDXID":"SPDXRef-maven-org.mockito-mockito-core-4.5.0","name":"maven:org.mockito:mockito-core","versionInfo":"4.5.0","downloadLocation":"NOASSERTION","filesAnalyzed":false,"licenseConcluded":"MIT","licenseDeclared":"NOASSERTION","supplier":"NOASSERTION","externalRefs":[{"referenceCategory":"PACKAGE-MANAGER","referenceLocator":"pkg:maven/org.mockito/mockito-core@4.5.0","referenceType":"purl"}]},{"SPDXID":"SPDXRef-maven-org.mockito-mockito-core-4.5.1","name":"maven:org.mockito:mockito-core","versionInfo":"4.5.1","downloadLocation":"NOASSERTION","filesAnalyzed":false,"licenseConcluded":"MIT","licenseDeclared":"NOASSERTION","supplier":"NOASSERTION","externalRefs":[{"referenceCategory":"PACKAGE-MANAGER","referenceLocator":"pkg:maven/org.mockito/mockito-core@4.5.1","referenceType":"purl"}]},{"SPDXID":"SPDXRef-maven-org.mockito-mockito-core-4.6.0","name":"maven:org.mockito:mockito-core","versionInfo":"4.6.0","downloadLocation":"NOASSERTION","filesAnalyzed":false,"licenseConcluded":"MIT","licenseDeclared":"NOASSERTION","supplier":"NOASSERTION","externalRefs":[{"referenceCategory":"PACKAGE-MANAGER","referenceLocator":"pkg:maven/org.mockito/mockito-core@4.6.0","referenceType":"purl"}]},{"SPDXID":"SPDXRef-maven-org.mockito-mockito-core-4.6.1","name":"maven:org.mockito:mockito-core","versionInfo":"4.6.1","downloadLocation":"NOASSERTION","filesAnalyzed":false,"licenseConcluded":"MIT","licenseDeclared":"NOASSERTION","supplier":"NOASSERTION","externalRefs":[{"referenceCategory":"PACKAGE-MANAGER","referenceLocator":"pkg:maven/org.mockito/mockito-core@4.6.1","referenceType":"purl"}]},{"SPDXID":"SPDXRef-maven-org.mockito-mockito-core-4.7.0","name":"maven:org.mockito:mockito-core","versionInfo":"4.7.0","downloadLocation":"NOASSERTION","filesAnalyzed":false,"licenseConcluded":"MIT","licenseDeclared":"NOASSERTION","supplier":"NOASSERTION","externalRefs":[{"referenceCategory":"PACKAGE-MANAGER","referenceLocator":"pkg:maven/org.mockito/mockito-core@4.7.0","referenceType":"purl"}]},{"SPDXID":"SPDXRef-maven-org.mockito-mockito-core-4.8.0","name":"maven:org.mockito:mockito-core","versionInfo":"4.8.0","downloadLocation":"NOASSERTION","filesAnalyzed":false,"licenseConcluded":"MIT","licenseDeclared":"NOASSERTION","supplier":"NOASSERTION","externalRefs":[{"referenceCategory":"PACKAGE-MANAGER","referenceLocator":"pkg:maven/org.mockito/mockito-core@4.8.0","referenceType":"purl"}]},{"SPDXID":"SPDXRef-maven-org.mockito-mockito-core-4.8.1","name":"maven:org.mockito:mockito-core","versionInfo":"4.8.1","downloadLocation":"NOASSERTION","filesAnalyzed":false,"licenseConcluded":"MIT","licenseDeclared":"NOASSERTION","supplier":"NOASSERTION","externalRefs":[{"referenceCategory":"PACKAGE-MANAGER","referenceLocator":"pkg:maven/org.mockito/mockito-core@4.8.1","referenceType":"purl"}]},{"SPDXID":"SPDXRef-maven-org.mockito-mockito-core-4.9.0","name":"maven:org.mockito:mockito-core","versionInfo":"4.9.0","downloadLocation":"NOASSERTION","filesAnalyzed":false,"licenseConcluded":"NOASSERTION","licenseDeclared":"NOASSERTION","supplier":"NOASSERTION","externalRefs":[{"referenceCategory":"PACKAGE-MANAGER","referenceLocator":"pkg:maven/org.mockito/mockito-core@4.9.0","referenceType":"purl"}]},{"SPDXID":"SPDXRef-maven-org.mockito-mockito-core-5.0.0","name":"maven:org.mockito:mockito-core","versionInfo":"5.0.0","downloadLocation":"NOASSERTION","filesAnalyzed":false,"licenseConcluded":"MIT","licenseDeclared":"NOASSERTION","supplier":"NOASSERTION","externalRefs":[{"referenceCategory":"PACKAGE-MANAGER","referenceLocator":"pkg:maven/org.mockito/mockito-core@5.0.0","referenceType":"purl"}]},{"SPDXID":"SPDXRef-maven-org.mockito-mockito-core-5.1.0","name":"maven:org.mockito:mockito-core","versionInfo":"5.1.0","downloadLocation":"NOASSERTION","filesAnalyzed":false,"licenseConcluded":"MIT","licenseDeclared":"NOASSERTION","supplier":"NOASSERTION","externalRefs":[{"referenceCategory":"PACKAGE-MANAGER","referenceLocator":"pkg:maven/org.mockito/mockito-core@5.1.0","referenceType":"purl"}]},{"SPDXID":"SPDXRef-maven-org.mockito-mockito-core-5.1.1","name":"maven:org.mockito:mockito-core","versionInfo":"5.1.1","downloadLocation":"NOASSERTION","filesAnalyzed":false,"licenseConcluded":"MIT","licenseDeclared":"NOASSERTION","supplier":"NOASSERTION","externalRefs":[{"referenceCategory":"PACKAGE-MANAGER","referenceLocator":"pkg:maven/org.mockito/mockito-core@5.1.1","referenceType":"purl"}]},{"SPDXID":"SPDXRef-maven-org.mockito-mockito-core-5.2.0","name":"maven:org.mockito:mockito-core","versionInfo":"5.2.0","downloadLocation":"NOASSERTION","filesAnalyzed":false,"licenseConcluded":"MIT","licenseDeclared":"NOASSERTION","supplier":"NOASSERTION","externalRefs":[{"referenceCategory":"PACKAGE-MANAGER","referenceLocator":"pkg:maven/org.mockito/mockito-core@5.2.0","referenceType":"purl"}]},{"SPDXID":"SPDXRef-maven-org.mockito-mockito-core-5.3.0","name":"maven:org.mockito:mockito-core","versionInfo":"5.3.0","downloadLocation":"NOASSERTION","filesAnalyzed":false,"licenseConcluded":"MIT","licenseDeclared":"NOASSERTION","supplier":"NOASSERTION","externalRefs":[{"referenceCategory":"PACKAGE-MANAGER","referenceLocator":"pkg:maven/org.mockito/mockito-core@5.3.0","referenceType":"purl"}]},{"SPDXID":"SPDXRef-maven-org.mockito-mockito-core-5.3.1","name":"maven:org.mockito:mockito-core","versionInfo":"5.3.1","downloadLocation":"NOASSERTION","filesAnalyzed":false,"licenseConcluded":"MIT","licenseDeclared":"NOASSERTION","supplier":"NOASSERTION","externalRefs":[{"referenceCategory":"PACKAGE-MANAGER","referenceLocator":"pkg:maven/org.mockito/mockito-core@5.3.1","referenceType":"purl"}]},{"SPDXID":"SPDXRef-maven-org.mockito-mockito-junit-jupiter-4.10.0","name":"maven:org.mockito:mockito-junit-jupiter","versionInfo":"4.10.0","downloadLocation":"NOASSERTION","filesAnalyzed":false,"licenseConcluded":"NOASSERTION","licenseDeclared":"NOASSERTION","supplier":"NOASSERTION","externalRefs":[{"referenceCategory":"PACKAGE-MANAGER","referenceLocator":"pkg:maven/org.mockito/mockito-junit-jupiter@4.10.0","referenceType":"purl"}]},{"SPDXID":"SPDXRef-maven-org.mockito-mockito-junit-jupiter-4.11.0","name":"maven:org.mockito:mockito-junit-jupiter","versionInfo":"4.11.0","downloadLocation":"NOASSERTION","filesAnalyzed":false,"licenseConcluded":"MIT","licenseDeclared":"NOASSERTION","supplier":"NOASSERTION","externalRefs":[{"referenceCategory":"PACKAGE-MANAGER","referenceLocator":"pkg:maven/org.mockito/mockito-junit-jupiter@4.11.0","referenceType":"purl"}]},{"SPDXID":"SPDXRef-maven-org.mockito-mockito-junit-jupiter-4.3.1","name":"maven:org.mockito:mockito-junit-jupiter","versionInfo":"4.3.1","downloadLocation":"NOASSERTION","filesAnalyzed":false,"licenseConcluded":"MIT","licenseDeclared":"NOASSERTION","supplier":"NOASSERTION","externalRefs":[{"referenceCategory":"PACKAGE-MANAGER","referenceLocator":"pkg:maven/org.mockito/mockito-junit-jupiter@4.3.1","referenceType":"purl"}]},{"SPDXID":"SPDXRef-maven-org.mockito-mockito-junit-jupiter-4.4.0","name":"maven:org.mockito:mockito-junit-jupiter","versionInfo":"4.4.0","downloadLocation":"NOASSERTION","filesAnalyzed":false,"licenseConcluded":"MIT","licenseDeclared":"NOASSERTION","supplier":"NOASSERTION","externalRefs":[{"referenceCategory":"PACKAGE-MANAGER","referenceLocator":"pkg:maven/org.mockito/mockito-junit-jupiter@4.4.0","referenceType":"purl"}]},{"SPDXID":"SPDXRef-maven-org.mockito-mockito-junit-jupiter-4.5.0","name":"maven:org.mockito:mockito-junit-jupiter","versionInfo":"4.5.0","downloadLocation":"NOASSERTION","filesAnalyzed":false,"licenseConcluded":"NOASSERTION","licenseDeclared":"NOASSERTION","supplier":"NOASSERTION","externalRefs":[{"referenceCategory":"PACKAGE-MANAGER","referenceLocator":"pkg:maven/org.mockito/mockito-junit-jupiter@4.5.0","referenceType":"purl"}]},{"SPDXID":"SPDXRef-maven-org.mockito-mockito-junit-jupiter-4.5.1","name":"maven:org.mockito:mockito-junit-jupiter","versionInfo":"4.5.1","downloadLocation":"NOASSERTION","filesAnalyzed":false,"licenseConcluded":"MIT","licenseDeclared":"NOASSERTION","supplier":"NOASSERTION","externalRefs":[{"referenceCategory":"PACKAGE-MANAGER","referenceLocator":"pkg:maven/org.mockito/mockito-junit-jupiter@4.5.1","referenceType":"purl"}]},{"SPDXID":"SPDXRef-maven-org.mockito-mockito-junit-jupiter-4.6.0","name":"maven:org.mockito:mockito-junit-jupiter","versionInfo":"4.6.0","downloadLocation":"NOASSERTION","filesAnalyzed":false,"licenseConcluded":"MIT","licenseDeclared":"NOASSERTION","supplier":"NOASSERTION","externalRefs":[{"referenceCategory":"PACKAGE-MANAGER","referenceLocator":"pkg:maven/org.mockito/mockito-junit-jupiter@4.6.0","referenceType":"purl"}]},{"SPDXID":"SPDXRef-maven-org.mockito-mockito-junit-jupiter-4.6.1","name":"maven:org.mockito:mockito-junit-jupiter","versionInfo":"4.6.1","downloadLocation":"NOASSERTION","filesAnalyzed":false,"licenseConcluded":"MIT","licenseDeclared":"NOASSERTION","supplier":"NOASSERTION","externalRefs":[{"referenceCategory":"PACKAGE-MANAGER","referenceLocator":"pkg:maven/org.mockito/mockito-junit-jupiter@4.6.1","referenceType":"purl"}]},{"SPDXID":"SPDXRef-maven-org.mockito-mockito-junit-jupiter-4.7.0","name":"maven:org.mockito:mockito-junit-jupiter","versionInfo":"4.7.0","downloadLocation":"NOASSERTION","filesAnalyzed":false,"licenseConcluded":"MIT","licenseDeclared":"NOASSERTION","supplier":"NOASSERTION","externalRefs":[{"referenceCategory":"PACKAGE-MANAGER","referenceLocator":"pkg:maven/org.mockito/mockito-junit-jupiter@4.7.0","referenceType":"purl"}]},{"SPDXID":"SPDXRef-maven-org.mockito-mockito-junit-jupiter-4.8.0","name":"maven:org.mockito:mockito-junit-jupiter","versionInfo":"4.8.0","downloadLocation":"NOASSERTION","filesAnalyzed":false,"licenseConcluded":"MIT","licenseDeclared":"NOASSERTION","supplier":"NOASSERTION","externalRefs":[{"referenceCategory":"PACKAGE-MANAGER","referenceLocator":"pkg:maven/org.mockito/mockito-junit-jupiter@4.8.0","referenceType":"purl"}]},{"SPDXID":"SPDXRef-maven-org.mockito-mockito-junit-jupiter-4.8.1","name":"maven:org.mockito:mockito-junit-jupiter","versionInfo":"4.8.1","downloadLocation":"NOASSERTION","filesAnalyzed":false,"licenseConcluded":"MIT","licenseDeclared":"NOASSERTION","supplier":"NOASSERTION","externalRefs":[{"referenceCategory":"PACKAGE-MANAGER","referenceLocator":"pkg:maven/org.mockito/mockito-junit-jupiter@4.8.1","referenceType":"purl"}]},{"SPDXID":"SPDXRef-maven-org.mockito-mockito-junit-jupiter-4.9.0","name":"maven:org.mockito:mockito-junit-jupiter","versionInfo":"4.9.0","downloadLocation":"NOASSERTION","filesAnalyzed":false,"licenseConcluded":"MIT","licenseDeclared":"NOASSERTION","supplier":"NOASSERTION","externalRefs":[{"referenceCategory":"PACKAGE-MANAGER","referenceLocator":"pkg:maven/org.mockito/mockito-junit-jupiter@4.9.0","referenceType":"purl"}]},{"SPDXID":"SPDXRef-maven-org.mockito-mockito-junit-jupiter-5.0.0","name":"maven:org.mockito:mockito-junit-jupiter","versionInfo":"5.0.0","downloadLocation":"NOASSERTION","filesAnalyzed":false,"licenseConcluded":"MIT","licenseDeclared":"NOASSERTION","supplier":"NOASSERTION","externalRefs":[{"referenceCategory":"PACKAGE-MANAGER","referenceLocator":"pkg:maven/org.mockito/mockito-junit-jupiter@5.0.0","referenceType":"purl"}]},{"SPDXID":"SPDXRef-maven-org.mockito-mockito-junit-jupiter-5.1.0","name":"maven:org.mockito:mockito-junit-jupiter","versionInfo":"5.1.0","downloadLocation":"NOASSERTION","filesAnalyzed":false,"licenseConcluded":"NOASSERTION","licenseDeclared":"NOASSERTION","supplier":"NOASSERTION","externalRefs":[{"referenceCategory":"PACKAGE-MANAGER","referenceLocator":"pkg:maven/org.mockito/mockito-junit-jupiter@5.1.0","referenceType":"purl"}]},{"SPDXID":"SPDXRef-maven-org.mockito-mockito-junit-jupiter-5.1.1","name":"maven:org.mockito:mockito-junit-jupiter","versionInfo":"5.1.1","downloadLocation":"NOASSERTION","filesAnalyzed":false,"licenseConcluded":"MIT","licenseDeclared":"NOASSERTION","supplier":"NOASSERTION","externalRefs":[{"referenceCategory":"PACKAGE-MANAGER","referenceLocator":"pkg:maven/org.mockito/mockito-junit-jupiter@5.1.1","referenceType":"purl"}]},{"SPDXID":"SPDXRef-maven-org.mockito-mockito-junit-jupiter-5.2.0","name":"maven:org.mockito:mockito-junit-jupiter","versionInfo":"5.2.0","downloadLocation":"NOASSERTION","filesAnalyzed":false,"licenseConcluded":"MIT","licenseDeclared":"NOASSERTION","supplier":"NOASSERTION","externalRefs":[{"referenceCategory":"PACKAGE-MANAGER","referenceLocator":"pkg:maven/org.mockito/mockito-junit-jupiter@5.2.0","referenceType":"purl"}]},{"SPDXID":"SPDXRef-maven-org.mockito-mockito-junit-jupiter-5.3.0","name":"maven:org.mockito:mockito-junit-jupiter","versionInfo":"5.3.0","downloadLocation":"NOASSERTION","filesAnalyzed":false,"licenseConcluded":"MIT","licenseDeclared":"NOASSERTION","supplier":"NOASSERTION","externalRefs":[{"referenceCategory":"PACKAGE-MANAGER","referenceLocator":"pkg:maven/org.mockito/mockito-junit-jupiter@5.3.0","referenceType":"purl"}]},{"SPDXID":"SPDXRef-maven-org.mockito-mockito-junit-jupiter-5.3.1","name":"maven:org.mockito:mockito-junit-jupiter","versionInfo":"5.3.1","downloadLocation":"NOASSERTION","filesAnalyzed":false,"licenseConcluded":"MIT","licenseDeclared":"NOASSERTION","supplier":"NOASSERTION","externalRefs":[{"referenceCategory":"PACKAGE-MANAGER","referenceLocator":"pkg:maven/org.mockito/mockito-junit-jupiter@5.3.1","referenceType":"purl"}]},{"SPDXID":"SPDXRef-maven-org.mockito-mockito-subclass-5.0.0","name":"maven:org.mockito:mockito-subclass","versionInfo":"5.0.0","downloadLocation":"NOASSERTION","filesAnalyzed":false,"licenseConcluded":"NOASSERTION","licenseDeclared":"NOASSERTION","supplier":"NOASSERTION","externalRefs":[{"referenceCategory":"PACKAGE-MANAGER","referenceLocator":"pkg:maven/org.mockito/mockito-subclass@5.0.0","referenceType":"purl"}]},{"SPDXID":"SPDXRef-maven-org.mockito-mockito-subclass-5.1.0","name":"maven:org.mockito:mockito-subclass","versionInfo":"5.1.0","downloadLocation":"NOASSERTION","filesAnalyzed":false,"licenseConcluded":"NOASSERTION","licenseDeclared":"NOASSERTION","supplier":"NOASSERTION","externalRefs":[{"referenceCategory":"PACKAGE-MANAGER","referenceLocator":"pkg:maven/org.mockito/mockito-subclass@5.1.0","referenceType":"purl"}]},{"SPDXID":"SPDXRef-maven-org.mockito-mockito-subclass-5.1.1","name":"maven:org.mockito:mockito-subclass","versionInfo":"5.1.1","downloadLocation":"NOASSERTION","filesAnalyzed":false,"licenseConcluded":"NOASSERTION","licenseDeclared":"NOASSERTION","supplier":"NOASSERTION","externalRefs":[{"referenceCategory":"PACKAGE-MANAGER","referenceLocator":"pkg:maven/org.mockito/mockito-subclass@5.1.1","referenceType":"purl"}]},{"SPDXID":"SPDXRef-maven-org.mockito-mockito-subclass-5.2.0","name":"maven:org.mockito:mockito-subclass","versionInfo":"5.2.0","downloadLocation":"NOASSERTION","filesAnalyzed":false,"licenseConcluded":"NOASSERTION","licenseDeclared":"NOASSERTION","supplier":"NOASSERTION","externalRefs":[{"referenceCategory":"PACKAGE-MANAGER","referenceLocator":"pkg:maven/org.mockito/mockito-subclass@5.2.0","referenceType":"purl"}]},{"SPDXID":"SPDXRef-maven-org.mockito-mockito-subclass-5.3.0","name":"maven:org.mockito:mockito-subclass","versionInfo":"5.3.0","downloadLocation":"NOASSERTION","filesAnalyzed":false,"licenseConcluded":"NOASSERTION","licenseDeclared":"NOASSERTION","supplier":"NOASSERTION","externalRefs":[{"referenceCategory":"PACKAGE-MANAGER","referenceLocator":"pkg:maven/org.mockito/mockito-subclass@5.3.0","referenceType":"purl"}]},{"SPDXID":"SPDXRef-maven-org.mockito-mockito-subclass-5.3.1","name":"maven:org.mockito:mockito-subclass","versionInfo":"5.3.1","downloadLocation":"NOASSERTION","filesAnalyzed":false,"licenseConcluded":"NOASSERTION","licenseDeclared":"NOASSERTION","supplier":"NOASSERTION","externalRefs":[{"referenceCategory":"PACKAGE-MANAGER","referenceLocator":"pkg:maven/org.mockito/mockito-subclass@5.3.1","referenceType":"purl"}]},{"SPDXID":"SPDXRef-maven-org.postgresql-postgresql-42.3.1","name":"maven:org.postgresql:postgresql","versionInfo":"42.3.1","downloadLocation":"NOASSERTION","filesAnalyzed":false,"licenseConcluded":"BSD-2-Clause","licenseDeclared":"NOASSERTION","supplier":"NOASSERTION","externalRefs":[{"referenceCategory":"PACKAGE-MANAGER","referenceLocator":"pkg:maven/org.postgresql/postgresql@42.3.1","referenceType":"purl"}]},{"SPDXID":"SPDXRef-maven-org.postgresql-postgresql-42.3.2","name":"maven:org.postgresql:postgresql","versionInfo":"42.3.2","downloadLocation":"NOASSERTION","filesAnalyzed":false,"licenseConcluded":"BSD-2-Clause","licenseDeclared":"NOASSERTION","supplier":"NOASSERTION","externalRefs":[{"referenceCategory":"PACKAGE-MANAGER","referenceLocator":"pkg:maven/org.postgresql/postgresql@42.3.2","referenceType":"purl"}]},{"SPDXID":"SPDXRef-maven-org.postgresql-postgresql-42.3.3","name":"maven:org.postgresql:postgresql","versionInfo":"42.3.3","downloadLocation":"NOASSERTION","filesAnalyzed":false,"licenseConcluded":"BSD-2-Clause","licenseDeclared":"NOASSERTION","supplier":"NOASSERTION","externalRefs":[{"referenceCategory":"PACKAGE-MANAGER","referenceLocator":"pkg:maven/org.postgresql/postgresql@42.3.3","referenceType":"purl"}]},{"SPDXID":"SPDXRef-maven-org.postgresql-postgresql-42.3.4","name":"maven:org.postgresql:postgresql","versionInfo":"42.3.4","downloadLocation":"NOASSERTION","filesAnalyzed":false,"licenseConcluded":"BSD-2-Clause","licenseDeclared":"NOASSERTION","supplier":"NOASSERTION","externalRefs":[{"referenceCategory":"PACKAGE-MANAGER","referenceLocator":"pkg:maven/org.postgresql/postgresql@42.3.4","referenceType":"purl"}]},{"SPDXID":"SPDXRef-maven-org.postgresql-postgresql-42.3.5","name":"maven:org.postgresql:postgresql","versionInfo":"42.3.5","downloadLocation":"NOASSERTION","filesAnalyzed":false,"licenseConcluded":"BSD-2-Clause","licenseDeclared":"NOASSERTION","supplier":"NOASSERTION","externalRefs":[{"referenceCategory":"PACKAGE-MANAGER","referenceLocator":"pkg:maven/org.postgresql/postgresql@42.3.5","referenceType":"purl"}]},{"SPDXID":"SPDXRef-maven-org.postgresql-postgresql-42.3.6","name":"maven:org.postgresql:postgresql","versionInfo":"42.3.6","downloadLocation":"NOASSERTION","filesAnalyzed":false,"licenseConcluded":"BSD-2-Clause","licenseDeclared":"NOASSERTION","supplier":"NOASSERTION","externalRefs":[{"referenceCategory":"PACKAGE-MANAGER","referenceLocator":"pkg:maven/org.postgresql/postgresql@42.3.6","referenceType":"purl"}]},{"SPDXID":"SPDXRef-maven-org.postgresql-postgresql-42.4.0","name":"maven:org.postgresql:postgresql","versionInfo":"42.4.0","downloadLocation":"NOASSERTION","filesAnalyzed":false,"licenseConcluded":"BSD-2-Clause","licenseDeclared":"NOASSERTION","supplier":"NOASSERTION","externalRefs":[{"referenceCategory":"PACKAGE-MANAGER","referenceLocator":"pkg:maven/org.postgresql/postgresql@42.4.0","referenceType":"purl"}]},{"SPDXID":"SPDXRef-maven-org.postgresql-postgresql-42.4.1","name":"maven:org.postgresql:postgresql","versionInfo":"42.4.1","downloadLocation":"NOASSERTION","filesAnalyzed":false,"licenseConcluded":"BSD-2-Clause","licenseDeclared":"NOASSERTION","supplier":"NOASSERTION","externalRefs":[{"referenceCategory":"PACKAGE-MANAGER","referenceLocator":"pkg:maven/org.postgresql/postgresql@42.4.1","referenceType":"purl"}]},{"SPDXID":"SPDXRef-maven-org.postgresql-postgresql-42.4.2","name":"maven:org.postgresql:postgresql","versionInfo":"42.4.2","downloadLocation":"NOASSERTION","filesAnalyzed":false,"licenseConcluded":"BSD-2-Clause","licenseDeclared":"NOASSERTION","supplier":"NOASSERTION","externalRefs":[{"referenceCategory":"PACKAGE-MANAGER","referenceLocator":"pkg:maven/org.postgresql/postgresql@42.4.2","referenceType":"purl"}]},{"SPDXID":"SPDXRef-maven-org.postgresql-postgresql-42.5.0","name":"maven:org.postgresql:postgresql","versionInfo":"42.5.0","downloadLocation":"NOASSERTION","filesAnalyzed":false,"licenseConcluded":"BSD-2-Clause","licenseDeclared":"NOASSERTION","supplier":"NOASSERTION","externalRefs":[{"referenceCategory":"PACKAGE-MANAGER","referenceLocator":"pkg:maven/org.postgresql/postgresql@42.5.0","referenceType":"purl"}]},{"SPDXID":"SPDXRef-maven-org.postgresql-postgresql-42.5.1","name":"maven:org.postgresql:postgresql","versionInfo":"42.5.1","downloadLocation":"NOASSERTION","filesAnalyzed":false,"licenseConcluded":"BSD-2-Clause","licenseDeclared":"NOASSERTION","supplier":"NOASSERTION","externalRefs":[{"referenceCategory":"PACKAGE-MANAGER","referenceLocator":"pkg:maven/org.postgresql/postgresql@42.5.1","referenceType":"purl"}]},{"SPDXID":"SPDXRef-maven-org.postgresql-postgresql-42.5.2","name":"maven:org.postgresql:postgresql","versionInfo":"42.5.2","downloadLocation":"NOASSERTION","filesAnalyzed":false,"licenseConcluded":"BSD-2-Clause","licenseDeclared":"NOASSERTION","supplier":"NOASSERTION","externalRefs":[{"referenceCategory":"PACKAGE-MANAGER","referenceLocator":"pkg:maven/org.postgresql/postgresql@42.5.2","referenceType":"purl"}]},{"SPDXID":"SPDXRef-maven-org.postgresql-postgresql-42.5.3","name":"maven:org.postgresql:postgresql","versionInfo":"42.5.3","downloadLocation":"NOASSERTION","filesAnalyzed":false,"licenseConcluded":"BSD-2-Clause","licenseDeclared":"NOASSERTION","supplier":"NOASSERTION","externalRefs":[{"referenceCategory":"PACKAGE-MANAGER","referenceLocator":"pkg:maven/org.postgresql/postgresql@42.5.3","referenceType":"purl"}]},{"SPDXID":"SPDXRef-maven-org.postgresql-postgresql-42.5.4","name":"maven:org.postgresql:postgresql","versionInfo":"42.5.4","downloadLocation":"NOASSERTION","filesAnalyzed":false,"licenseConcluded":"BSD-2-Clause","licenseDeclared":"NOASSERTION","supplier":"NOASSERTION","externalRefs":[{"referenceCategory":"PACKAGE-MANAGER","referenceLocator":"pkg:maven/org.postgresql/postgresql@42.5.4","referenceType":"purl"}]},{"SPDXID":"SPDXRef-maven-org.postgresql-postgresql-42.6.0","name":"maven:org.postgresql:postgresql","versionInfo":"42.6.0","downloadLocation":"NOASSERTION","filesAnalyzed":false,"licenseConcluded":"BSD-2-Clause","licenseDeclared":"NOASSERTION","supplier":"NOASSERTION","externalRefs":[{"referenceCategory":"PACKAGE-MANAGER","referenceLocator":"pkg:maven/org.postgresql/postgresql@42.6.0","referenceType":"purl"}]},{"SPDXID":"SPDXRef-maven-org.slf4j-slf4j-api-1.7.35","name":"maven:org.slf4j:slf4j-api","versionInfo":"1.7.35","downloadLocation":"NOASSERTION","filesAnalyzed":false,"licenseConcluded":"MIT","licenseDeclared":"NOASSERTION","supplier":"NOASSERTION","externalRefs":[{"referenceCategory":"PACKAGE-MANAGER","referenceLocator":"pkg:maven/org.slf4j/slf4j-api@1.7.35","referenceType":"purl"}]},{"SPDXID":"SPDXRef-maven-org.slf4j-slf4j-api-1.7.36","name":"maven:org.slf4j:slf4j-api","versionInfo":"1.7.36","downloadLocation":"NOASSERTION","filesAnalyzed":false,"licenseConcluded":"MIT","licenseDeclared":"NOASSERTION","supplier":"NOASSERTION","externalRefs":[{"referenceCategory":"PACKAGE-MANAGER","referenceLocator":"pkg:maven/org.slf4j/slf4j-api@1.7.36","referenceType":"purl"}]},{"SPDXID":"SPDXRef-maven-org.slf4j-slf4j-api-2.0.0","name":"maven:org.slf4j:slf4j-api","versionInfo":"2.0.0","downloadLocation":"NOASSERTION","filesAnalyzed":false,"licenseConcluded":"MIT","licenseDeclared":"NOASSERTION","supplier":"NOASSERTION","externalRefs":[{"referenceCategory":"PACKAGE-MANAGER","referenceLocator":"pkg:maven/org.slf4j/slf4j-api@2.0.0","referenceType":"purl"}]},{"SPDXID":"SPDXRef-maven-org.slf4j-slf4j-api-2.0.1","name":"maven:org.slf4j:slf4j-api","versionInfo":"2.0.1","downloadLocation":"NOASSERTION","filesAnalyzed":false,"licenseConcluded":"MIT","licenseDeclared":"NOASSERTION","supplier":"NOASSERTION","externalRefs":[{"referenceCategory":"PACKAGE-MANAGER","referenceLocator":"pkg:maven/org.slf4j/slf4j-api@2.0.1","referenceType":"purl"}]},{"SPDXID":"SPDXRef-maven-org.slf4j-slf4j-api-2.0.2","name":"maven:org.slf4j:slf4j-api","versionInfo":"2.0.2","downloadLocation":"NOASSERTION","filesAnalyzed":false,"licenseConcluded":"MIT","licenseDeclared":"NOASSERTION","supplier":"NOASSERTION","externalRefs":[{"referenceCategory":"PACKAGE-MANAGER","referenceLocator":"pkg:maven/org.slf4j/slf4j-api@2.0.2","referenceType":"purl"}]},{"SPDXID":"SPDXRef-maven-org.slf4j-slf4j-api-2.0.3","name":"maven:org.slf4j:slf4j-api","versionInfo":"2.0.3","downloadLocation":"NOASSERTION","filesAnalyzed":false,"licenseConcluded":"MIT","licenseDeclared":"NOASSERTION","supplier":"NOASSERTION","externalRefs":[{"referenceCategory":"PACKAGE-MANAGER","referenceLocator":"pkg:maven/org.slf4j/slf4j-api@2.0.3","referenceType":"purl"}]},{"SPDXID":"SPDXRef-maven-org.slf4j-slf4j-api-2.0.4","name":"maven:org.slf4j:slf4j-api","versionInfo":"2.0.4","downloadLocation":"NOASSERTION","filesAnalyzed":false,"licenseConcluded":"MIT","licenseDeclared":"NOASSERTION","supplier":"NOASSERTION","externalRefs":[{"referenceCategory":"PACKAGE-MANAGER","referenceLocator":"pkg:maven/org.slf4j/slf4j-api@2.0.4","referenceType":"purl"}]},{"SPDXID":"SPDXRef-maven-org.slf4j-slf4j-api-2.0.5","name":"maven:org.slf4j:slf4j-api","versionInfo":"2.0.5","downloadLocation":"NOASSERTION","filesAnalyzed":false,"licenseConcluded":"MIT","licenseDeclared":"NOASSERTION","supplier":"NOASSERTION","externalRefs":[{"referenceCategory":"PACKAGE-MANAGER","referenceLocator":"pkg:maven/org.slf4j/slf4j-api@2.0.5","referenceType":"purl"}]},{"SPDXID":"SPDXRef-maven-org.slf4j-slf4j-api-2.0.6","name":"maven:org.slf4j:slf4j-api","versionInfo":"2.0.6","downloadLocation":"NOASSERTION","filesAnalyzed":false,"licenseConcluded":"MIT","licenseDeclared":"NOASSERTION","supplier":"NOASSERTION","externalRefs":[{"referenceCategory":"PACKAGE-MANAGER","referenceLocator":"pkg:maven/org.slf4j/slf4j-api@2.0.6","referenceType":"purl"}]},{"SPDXID":"SPDXRef-maven-org.slf4j-slf4j-api-2.0.7","name":"maven:org.slf4j:slf4j-api","versionInfo":"2.0.7","downloadLocation":"NOASSERTION","filesAnalyzed":false,"licenseConcluded":"MIT","licenseDeclared":"NOASSERTION","supplier":"NOASSERTION","externalRefs":[{"referenceCategory":"PACKAGE-MANAGER","referenceLocator":"pkg:maven/org.slf4j/slf4j-api@2.0.7","referenceType":"purl"}]},{"SPDXID":"SPDXRef-maven-org.slf4j-slf4j-log4j12-1.7.32","name":"maven:org.slf4j:slf4j-log4j12","versionInfo":"1.7.32","downloadLocation":"NOASSERTION","filesAnalyzed":false,"licenseConcluded":"MIT","licenseDeclared":"NOASSERTION","supplier":"NOASSERTION","externalRefs":[{"referenceCategory":"PACKAGE-MANAGER","referenceLocator":"pkg:maven/org.slf4j/slf4j-log4j12@1.7.32","referenceType":"purl"}]},{"SPDXID":"SPDXRef-maven-org.testcontainers-junit-jupiter-1.16.3","name":"maven:org.testcontainers:junit-jupiter","versionInfo":"1.16.3","downloadLocation":"NOASSERTION","filesAnalyzed":false,"licenseConcluded":"MIT","licenseDeclared":"NOASSERTION","supplier":"NOASSERTION","externalRefs":[{"referenceCategory":"PACKAGE-MANAGER","referenceLocator":"pkg:maven/org.testcontainers/junit-jupiter@1.16.3","referenceType":"purl"}]},{"SPDXID":"SPDXRef-maven-org.testcontainers-junit-jupiter-1.17.0","name":"maven:org.testcontainers:junit-jupiter","versionInfo":"1.17.0","downloadLocation":"NOASSERTION","filesAnalyzed":false,"licenseConcluded":"MIT","licenseDeclared":"NOASSERTION","supplier":"NOASSERTION","externalRefs":[{"referenceCategory":"PACKAGE-MANAGER","referenceLocator":"pkg:maven/org.testcontainers/junit-jupiter@1.17.0","referenceType":"purl"}]},{"SPDXID":"SPDXRef-maven-org.testcontainers-junit-jupiter-1.17.1","name":"maven:org.testcontainers:junit-jupiter","versionInfo":"1.17.1","downloadLocation":"NOASSERTION","filesAnalyzed":false,"licenseConcluded":"MIT","licenseDeclared":"NOASSERTION","supplier":"NOASSERTION","externalRefs":[{"referenceCategory":"PACKAGE-MANAGER","referenceLocator":"pkg:maven/org.testcontainers/junit-jupiter@1.17.1","referenceType":"purl"}]},{"SPDXID":"SPDXRef-maven-org.testcontainers-junit-jupiter-1.17.2","name":"maven:org.testcontainers:junit-jupiter","versionInfo":"1.17.2","downloadLocation":"NOASSERTION","filesAnalyzed":false,"licenseConcluded":"MIT","licenseDeclared":"NOASSERTION","supplier":"NOASSERTION","externalRefs":[{"referenceCategory":"PACKAGE-MANAGER","referenceLocator":"pkg:maven/org.testcontainers/junit-jupiter@1.17.2","referenceType":"purl"}]},{"SPDXID":"SPDXRef-maven-org.testcontainers-junit-jupiter-1.17.3","name":"maven:org.testcontainers:junit-jupiter","versionInfo":"1.17.3","downloadLocation":"NOASSERTION","filesAnalyzed":false,"licenseConcluded":"MIT","licenseDeclared":"NOASSERTION","supplier":"NOASSERTION","externalRefs":[{"referenceCategory":"PACKAGE-MANAGER","referenceLocator":"pkg:maven/org.testcontainers/junit-jupiter@1.17.3","referenceType":"purl"}]},{"SPDXID":"SPDXRef-maven-org.testcontainers-junit-jupiter-1.17.4","name":"maven:org.testcontainers:junit-jupiter","versionInfo":"1.17.4","downloadLocation":"NOASSERTION","filesAnalyzed":false,"licenseConcluded":"MIT","licenseDeclared":"NOASSERTION","supplier":"NOASSERTION","externalRefs":[{"referenceCategory":"PACKAGE-MANAGER","referenceLocator":"pkg:maven/org.testcontainers/junit-jupiter@1.17.4","referenceType":"purl"}]},{"SPDXID":"SPDXRef-maven-org.testcontainers-junit-jupiter-1.17.5","name":"maven:org.testcontainers:junit-jupiter","versionInfo":"1.17.5","downloadLocation":"NOASSERTION","filesAnalyzed":false,"licenseConcluded":"MIT","licenseDeclared":"NOASSERTION","supplier":"NOASSERTION","externalRefs":[{"referenceCategory":"PACKAGE-MANAGER","referenceLocator":"pkg:maven/org.testcontainers/junit-jupiter@1.17.5","referenceType":"purl"}]},{"SPDXID":"SPDXRef-maven-org.testcontainers-junit-jupiter-1.17.6","name":"maven:org.testcontainers:junit-jupiter","versionInfo":"1.17.6","downloadLocation":"NOASSERTION","filesAnalyzed":false,"licenseConcluded":"MIT","licenseDeclared":"NOASSERTION","supplier":"NOASSERTION","externalRefs":[{"referenceCategory":"PACKAGE-MANAGER","referenceLocator":"pkg:maven/org.testcontainers/junit-jupiter@1.17.6","referenceType":"purl"}]},{"SPDXID":"SPDXRef-maven-org.testcontainers-junit-jupiter-1.18.0","name":"maven:org.testcontainers:junit-jupiter","versionInfo":"1.18.0","downloadLocation":"NOASSERTION","filesAnalyzed":false,"licenseConcluded":"NOASSERTION","licenseDeclared":"NOASSERTION","supplier":"NOASSERTION","externalRefs":[{"referenceCategory":"PACKAGE-MANAGER","referenceLocator":"pkg:maven/org.testcontainers/junit-jupiter@1.18.0","referenceType":"purl"}]},{"SPDXID":"SPDXRef-maven-org.testcontainers-junit-jupiter-1.18.1","name":"maven:org.testcontainers:junit-jupiter","versionInfo":"1.18.1","downloadLocation":"NOASSERTION","filesAnalyzed":false,"licenseConcluded":"NOASSERTION","licenseDeclared":"NOASSERTION","supplier":"NOASSERTION","externalRefs":[{"referenceCategory":"PACKAGE-MANAGER","referenceLocator":"pkg:maven/org.testcontainers/junit-jupiter@1.18.1","referenceType":"purl"}]},{"SPDXID":"SPDXRef-maven-org.testcontainers-mysql-1.16.3","name":"maven:org.testcontainers:mysql","versionInfo":"1.16.3","downloadLocation":"NOASSERTION","filesAnalyzed":false,"licenseConcluded":"MIT","licenseDeclared":"NOASSERTION","supplier":"NOASSERTION","externalRefs":[{"referenceCategory":"PACKAGE-MANAGER","referenceLocator":"pkg:maven/org.testcontainers/mysql@1.16.3","referenceType":"purl"}]},{"SPDXID":"SPDXRef-maven-org.testcontainers-mysql-1.17.0","name":"maven:org.testcontainers:mysql","versionInfo":"1.17.0","downloadLocation":"NOASSERTION","filesAnalyzed":false,"licenseConcluded":"MIT","licenseDeclared":"NOASSERTION","supplier":"NOASSERTION","externalRefs":[{"referenceCategory":"PACKAGE-MANAGER","referenceLocator":"pkg:maven/org.testcontainers/mysql@1.17.0","referenceType":"purl"}]},{"SPDXID":"SPDXRef-maven-org.testcontainers-mysql-1.17.1","name":"maven:org.testcontainers:mysql","versionInfo":"1.17.1","downloadLocation":"NOASSERTION","filesAnalyzed":false,"licenseConcluded":"MIT","licenseDeclared":"NOASSERTION","supplier":"NOASSERTION","externalRefs":[{"referenceCategory":"PACKAGE-MANAGER","referenceLocator":"pkg:maven/org.testcontainers/mysql@1.17.1","referenceType":"purl"}]},{"SPDXID":"SPDXRef-maven-org.testcontainers-mysql-1.17.2","name":"maven:org.testcontainers:mysql","versionInfo":"1.17.2","downloadLocation":"NOASSERTION","filesAnalyzed":false,"licenseConcluded":"MIT","licenseDeclared":"NOASSERTION","supplier":"NOASSERTION","externalRefs":[{"referenceCategory":"PACKAGE-MANAGER","referenceLocator":"pkg:maven/org.testcontainers/mysql@1.17.2","referenceType":"purl"}]},{"SPDXID":"SPDXRef-maven-org.testcontainers-mysql-1.17.3","name":"maven:org.testcontainers:mysql","versionInfo":"1.17.3","downloadLocation":"NOASSERTION","filesAnalyzed":false,"licenseConcluded":"MIT","licenseDeclared":"NOASSERTION","supplier":"NOASSERTION","externalRefs":[{"referenceCategory":"PACKAGE-MANAGER","referenceLocator":"pkg:maven/org.testcontainers/mysql@1.17.3","referenceType":"purl"}]},{"SPDXID":"SPDXRef-maven-org.testcontainers-mysql-1.17.4","name":"maven:org.testcontainers:mysql","versionInfo":"1.17.4","downloadLocation":"NOASSERTION","filesAnalyzed":false,"licenseConcluded":"MIT","licenseDeclared":"NOASSERTION","supplier":"NOASSERTION","externalRefs":[{"referenceCategory":"PACKAGE-MANAGER","referenceLocator":"pkg:maven/org.testcontainers/mysql@1.17.4","referenceType":"purl"}]},{"SPDXID":"SPDXRef-maven-org.testcontainers-mysql-1.17.5","name":"maven:org.testcontainers:mysql","versionInfo":"1.17.5","downloadLocation":"NOASSERTION","filesAnalyzed":false,"licenseConcluded":"MIT","licenseDeclared":"NOASSERTION","supplier":"NOASSERTION","externalRefs":[{"referenceCategory":"PACKAGE-MANAGER","referenceLocator":"pkg:maven/org.testcontainers/mysql@1.17.5","referenceType":"purl"}]},{"SPDXID":"SPDXRef-maven-org.testcontainers-mysql-1.17.6","name":"maven:org.testcontainers:mysql","versionInfo":"1.17.6","downloadLocation":"NOASSERTION","filesAnalyzed":false,"licenseConcluded":"MIT","licenseDeclared":"NOASSERTION","supplier":"NOASSERTION","externalRefs":[{"referenceCategory":"PACKAGE-MANAGER","referenceLocator":"pkg:maven/org.testcontainers/mysql@1.17.6","referenceType":"purl"}]},{"SPDXID":"SPDXRef-maven-org.testcontainers-mysql-1.18.0","name":"maven:org.testcontainers:mysql","versionInfo":"1.18.0","downloadLocation":"NOASSERTION","filesAnalyzed":false,"licenseConcluded":"NOASSERTION","licenseDeclared":"NOASSERTION","supplier":"NOASSERTION","externalRefs":[{"referenceCategory":"PACKAGE-MANAGER","referenceLocator":"pkg:maven/org.testcontainers/mysql@1.18.0","referenceType":"purl"}]},{"SPDXID":"SPDXRef-maven-org.testcontainers-mysql-1.18.1","name":"maven:org.testcontainers:mysql","versionInfo":"1.18.1","downloadLocation":"NOASSERTION","filesAnalyzed":false,"licenseConcluded":"NOASSERTION","licenseDeclared":"NOASSERTION","supplier":"NOASSERTION","externalRefs":[{"referenceCategory":"PACKAGE-MANAGER","referenceLocator":"pkg:maven/org.testcontainers/mysql@1.18.1","referenceType":"purl"}]},{"SPDXID":"SPDXRef-maven-org.testcontainers-postgresql-1.16.3","name":"maven:org.testcontainers:postgresql","versionInfo":"1.16.3","downloadLocation":"NOASSERTION","filesAnalyzed":false,"licenseConcluded":"MIT","licenseDeclared":"NOASSERTION","supplier":"NOASSERTION","externalRefs":[{"referenceCategory":"PACKAGE-MANAGER","referenceLocator":"pkg:maven/org.testcontainers/postgresql@1.16.3","referenceType":"purl"}]},{"SPDXID":"SPDXRef-maven-org.testcontainers-postgresql-1.17.0","name":"maven:org.testcontainers:postgresql","versionInfo":"1.17.0","downloadLocation":"NOASSERTION","filesAnalyzed":false,"licenseConcluded":"MIT","licenseDeclared":"NOASSERTION","supplier":"NOASSERTION","externalRefs":[{"referenceCategory":"PACKAGE-MANAGER","referenceLocator":"pkg:maven/org.testcontainers/postgresql@1.17.0","referenceType":"purl"}]},{"SPDXID":"SPDXRef-maven-org.testcontainers-postgresql-1.17.1","name":"maven:org.testcontainers:postgresql","versionInfo":"1.17.1","downloadLocation":"NOASSERTION","filesAnalyzed":false,"licenseConcluded":"MIT","licenseDeclared":"NOASSERTION","supplier":"NOASSERTION","externalRefs":[{"referenceCategory":"PACKAGE-MANAGER","referenceLocator":"pkg:maven/org.testcontainers/postgresql@1.17.1","referenceType":"purl"}]},{"SPDXID":"SPDXRef-maven-org.testcontainers-postgresql-1.17.2","name":"maven:org.testcontainers:postgresql","versionInfo":"1.17.2","downloadLocation":"NOASSERTION","filesAnalyzed":false,"licenseConcluded":"MIT","licenseDeclared":"NOASSERTION","supplier":"NOASSERTION","externalRefs":[{"referenceCategory":"PACKAGE-MANAGER","referenceLocator":"pkg:maven/org.testcontainers/postgresql@1.17.2","referenceType":"purl"}]},{"SPDXID":"SPDXRef-maven-org.testcontainers-postgresql-1.17.3","name":"maven:org.testcontainers:postgresql","versionInfo":"1.17.3","downloadLocation":"NOASSERTION","filesAnalyzed":false,"licenseConcluded":"MIT","licenseDeclared":"NOASSERTION","supplier":"NOASSERTION","externalRefs":[{"referenceCategory":"PACKAGE-MANAGER","referenceLocator":"pkg:maven/org.testcontainers/postgresql@1.17.3","referenceType":"purl"}]},{"SPDXID":"SPDXRef-maven-org.testcontainers-postgresql-1.17.4","name":"maven:org.testcontainers:postgresql","versionInfo":"1.17.4","downloadLocation":"NOASSERTION","filesAnalyzed":false,"licenseConcluded":"MIT","licenseDeclared":"NOASSERTION","supplier":"NOASSERTION","externalRefs":[{"referenceCategory":"PACKAGE-MANAGER","referenceLocator":"pkg:maven/org.testcontainers/postgresql@1.17.4","referenceType":"purl"}]},{"SPDXID":"SPDXRef-maven-org.testcontainers-postgresql-1.17.5","name":"maven:org.testcontainers:postgresql","versionInfo":"1.17.5","downloadLocation":"NOASSERTION","filesAnalyzed":false,"licenseConcluded":"MIT","licenseDeclared":"NOASSERTION","supplier":"NOASSERTION","externalRefs":[{"referenceCategory":"PACKAGE-MANAGER","referenceLocator":"pkg:maven/org.testcontainers/postgresql@1.17.5","referenceType":"purl"}]},{"SPDXID":"SPDXRef-maven-org.testcontainers-postgresql-1.17.6","name":"maven:org.testcontainers:postgresql","versionInfo":"1.17.6","downloadLocation":"NOASSERTION","filesAnalyzed":false,"licenseConcluded":"MIT","licenseDeclared":"NOASSERTION","supplier":"NOASSERTION","externalRefs":[{"referenceCategory":"PACKAGE-MANAGER","referenceLocator":"pkg:maven/org.testcontainers/postgresql@1.17.6","referenceType":"purl"}]},{"SPDXID":"SPDXRef-maven-org.testcontainers-postgresql-1.18.0","name":"maven:org.testcontainers:postgresql","versionInfo":"1.18.0","downloadLocation":"NOASSERTION","filesAnalyzed":false,"licenseConcluded":"NOASSERTION","licenseDeclared":"NOASSERTION","supplier":"NOASSERTION","externalRefs":[{"referenceCategory":"PACKAGE-MANAGER","referenceLocator":"pkg:maven/org.testcontainers/postgresql@1.18.0","referenceType":"purl"}]},{"SPDXID":"SPDXRef-maven-org.testcontainers-postgresql-1.18.1","name":"maven:org.testcontainers:postgresql","versionInfo":"1.18.1","downloadLocation":"NOASSERTION","filesAnalyzed":false,"licenseConcluded":"NOASSERTION","licenseDeclared":"NOASSERTION","supplier":"NOASSERTION","externalRefs":[{"referenceCategory":"PACKAGE-MANAGER","referenceLocator":"pkg:maven/org.testcontainers/postgresql@1.18.1","referenceType":"purl"}]},{"SPDXID":"SPDXRef-maven-ru.yandex.qatools.embed-postgresql-embedded-2.10","name":"maven:ru.yandex.qatools.embed:postgresql-embedded","versionInfo":"2.10","downloadLocation":"NOASSERTION","filesAnalyzed":false,"licenseConcluded":"Apache-2.0","licenseDeclared":"NOASSERTION","supplier":"NOASSERTION","externalRefs":[{"referenceCategory":"PACKAGE-MANAGER","referenceLocator":"pkg:maven/ru.yandex.qatools.embed/postgresql-embedded@2.10","referenceType":"purl"}]},{"SPDXID":"SPDXRef-actions-actions-cache-2","name":"actions:actions/cache","versionInfo":"2","downloadLocation":"NOASSERTION","filesAnalyzed":false,"licenseConcluded":"NOASSERTION","licenseDeclared":"NOASSERTION","supplier":"NOASSERTION","externalRefs":[{"referenceCategory":"PACKAGE-MANAGER","referenceLocator":"pkg:githubactions/actions/cache@2","referenceType":"purl"}]},{"SPDXID":"SPDXRef-actions-actions-cache-3","name":"actions:actions/cache","versionInfo":"3","downloadLocation":"NOASSERTION","filesAnalyzed":false,"licenseConcluded":"NOASSERTION","licenseDeclared":"NOASSERTION","supplier":"NOASSERTION","externalRefs":[{"referenceCategory":"PACKAGE-MANAGER","referenceLocator":"pkg:githubactions/actions/cache@3","referenceType":"purl"}]},{"SPDXID":"SPDXRef-actions-actions-checkout-2","name":"actions:actions/checkout","versionInfo":"2","downloadLocation":"NOASSERTION","filesAnalyzed":false,"licenseConcluded":"NOASSERTION","licenseDeclared":"NOASSERTION","supplier":"NOASSERTION","externalRefs":[{"referenceCategory":"PACKAGE-MANAGER","referenceLocator":"pkg:githubactions/actions/checkout@2","referenceType":"purl"}]},{"SPDXID":"SPDXRef-actions-actions-checkout-3","name":"actions:actions/checkout","versionInfo":"3","downloadLocation":"NOASSERTION","filesAnalyzed":false,"licenseConcluded":"NOASSERTION","licenseDeclared":"NOASSERTION","supplier":"NOASSERTION","externalRefs":[{"referenceCategory":"PACKAGE-MANAGER","referenceLocator":"pkg:githubactions/actions/checkout@3","referenceType":"purl"}]},{"SPDXID":"SPDXRef-actions-actions-setup-java-2","name":"actions:actions/setup-java","versionInfo":"2","downloadLocation":"NOASSERTION","filesAnalyzed":false,"licenseConcluded":"NOASSERTION","licenseDeclared":"NOASSERTION","supplier":"NOASSERTION","externalRefs":[{"referenceCategory":"PACKAGE-MANAGER","referenceLocator":"pkg:githubactions/actions/setup-java@2","referenceType":"purl"}]},{"SPDXID":"SPDXRef-actions-actions-setup-java-3","name":"actions:actions/setup-java","versionInfo":"3","downloadLocation":"NOASSERTION","filesAnalyzed":false,"licenseConcluded":"NOASSERTION","licenseDeclared":"NOASSERTION","supplier":"NOASSERTION","externalRefs":[{"referenceCategory":"PACKAGE-MANAGER","referenceLocator":"pkg:githubactions/actions/setup-java@3","referenceType":"purl"}]},{"SPDXID":"SPDXRef-actions-oracle-actions-setup-java-1","name":"actions:oracle-actions/setup-java","versionInfo":"1","downloadLocation":"NOASSERTION","filesAnalyzed":false,"licenseConcluded":"NOASSERTION","licenseDeclared":"NOASSERTION","supplier":"NOASSERTION","externalRefs":[{"referenceCategory":"PACKAGE-MANAGER","referenceLocator":"pkg:githubactions/oracle-actions/setup-java@1","referenceType":"purl"}]}]}